{
"meta":{"test_sets":[],"test_metrics":[],"learn_metrics":[{"best_value":"Min","name":"RMSE"}],"launch_mode":"Train","parameters":"","iteration_count":1000,"learn_sets":["learn"],"name":"experiment"},
"iterations":[
{"learn":[14.59871775],"iteration":0,"passed_time":0.05451710362,"remaining_time":54.46258652},
{"learn":[14.22518863],"iteration":1,"passed_time":0.05551088975,"remaining_time":27.69993399},
{"learn":[13.8866124],"iteration":2,"passed_time":0.05647917968,"remaining_time":18.76991405},
{"learn":[13.52356875],"iteration":3,"passed_time":0.05737796186,"remaining_time":14.2871125},
{"learn":[13.18870211],"iteration":4,"passed_time":0.05860202007,"remaining_time":11.66180199},
{"learn":[12.9124226],"iteration":5,"passed_time":0.0599265875,"remaining_time":9.927837996},
{"learn":[12.60003351],"iteration":6,"passed_time":0.06091239368,"remaining_time":8.640858133},
{"learn":[12.32990573],"iteration":7,"passed_time":0.06200755265,"remaining_time":7.688936529},
{"learn":[12.0660619],"iteration":8,"passed_time":0.06315322552,"remaining_time":6.953871832},
{"learn":[11.77309809],"iteration":9,"passed_time":0.06429556011,"remaining_time":6.365260451},
{"learn":[11.49227636],"iteration":10,"passed_time":0.06532502145,"remaining_time":5.873313292},
{"learn":[11.26264833],"iteration":11,"passed_time":0.0662275737,"remaining_time":5.452736902},
{"learn":[11.04260393],"iteration":12,"passed_time":0.06715175131,"remaining_time":5.098367581},
{"learn":[10.79916926],"iteration":13,"passed_time":0.06800008967,"remaining_time":4.789149173},
{"learn":[10.5541002],"iteration":14,"passed_time":0.06880599086,"remaining_time":4.518260066},
{"learn":[10.31918115],"iteration":15,"passed_time":0.06963890656,"remaining_time":4.282792753},
{"learn":[10.10004441],"iteration":16,"passed_time":0.07048678041,"remaining_time":4.07579442},
{"learn":[9.894556723],"iteration":17,"passed_time":0.07130858144,"remaining_time":3.890279276},
{"learn":[9.690174082],"iteration":18,"passed_time":0.07230795427,"remaining_time":3.73337385},
{"learn":[9.506034866],"iteration":19,"passed_time":0.07354409019,"remaining_time":3.603660419},
{"learn":[9.338524633],"iteration":20,"passed_time":0.07465497415,"remaining_time":3.480343795},
{"learn":[9.170203312],"iteration":21,"passed_time":0.07562572673,"remaining_time":3.361907307},
{"learn":[9.010299969],"iteration":22,"passed_time":0.0764223252,"remaining_time":3.246287466},
{"learn":[8.843866678],"iteration":23,"passed_time":0.07721047321,"remaining_time":3.139892577},
{"learn":[8.690548059],"iteration":24,"passed_time":0.07811154119,"remaining_time":3.046350107},
{"learn":[8.555307687],"iteration":25,"passed_time":0.07891328923,"remaining_time":2.956213219},
{"learn":[8.413851302],"iteration":26,"passed_time":0.07969102866,"remaining_time":2.871828551},
{"learn":[8.29256019],"iteration":27,"passed_time":0.08046493462,"remaining_time":2.79328273},
{"learn":[8.162193833],"iteration":28,"passed_time":0.08118530942,"remaining_time":2.718308119},
{"learn":[8.040736294],"iteration":29,"passed_time":0.08193046832,"remaining_time":2.649085142},
{"learn":[7.921220278],"iteration":30,"passed_time":0.08269972659,"remaining_time":2.585033389},
{"learn":[7.809589039],"iteration":31,"passed_time":0.08344023714,"remaining_time":2.524067174},
{"learn":[7.699675801],"iteration":32,"passed_time":0.0842267921,"remaining_time":2.468100241},
{"learn":[7.60645267],"iteration":33,"passed_time":0.08510709565,"remaining_time":2.418042776},
{"learn":[7.498880302],"iteration":34,"passed_time":0.0858938575,"remaining_time":2.368216357},
{"learn":[7.401158744],"iteration":35,"passed_time":0.08745000175,"remaining_time":2.341716713},
{"learn":[7.306431077],"iteration":36,"passed_time":0.08876502821,"remaining_time":2.310289788},
{"learn":[7.223863468],"iteration":37,"passed_time":0.08975280452,"remaining_time":2.272163104},
{"learn":[7.143477682],"iteration":38,"passed_time":0.09060831863,"remaining_time":2.232681903},
{"learn":[7.062817131],"iteration":39,"passed_time":0.09133929221,"remaining_time":2.192143013},
{"learn":[6.990793435],"iteration":40,"passed_time":0.09233736431,"remaining_time":2.159793473},
{"learn":[6.931862224],"iteration":41,"passed_time":0.09328852173,"remaining_time":2.127866758},
{"learn":[6.858296558],"iteration":42,"passed_time":0.09412521217,"remaining_time":2.09483321},
{"learn":[6.786268161],"iteration":43,"passed_time":0.09490904219,"remaining_time":2.062114644},
{"learn":[6.717118549],"iteration":44,"passed_time":0.09565258401,"remaining_time":2.029960394},
{"learn":[6.652948106],"iteration":45,"passed_time":0.09640237459,"remaining_time":1.999301421},
{"learn":[6.589686076],"iteration":46,"passed_time":0.09717644205,"remaining_time":1.970407431},
{"learn":[6.531283097],"iteration":47,"passed_time":0.09807734119,"remaining_time":1.9452006},
{"learn":[6.471368031],"iteration":48,"passed_time":0.09920336149,"remaining_time":1.925355036},
{"learn":[6.416481395],"iteration":49,"passed_time":0.1002695291,"remaining_time":1.905121054},
{"learn":[6.369870822],"iteration":50,"passed_time":0.1014128455,"remaining_time":1.88707432},
{"learn":[6.325678067],"iteration":51,"passed_time":0.1024400697,"remaining_time":1.867561271},
{"learn":[6.275766122],"iteration":52,"passed_time":0.1034485564,"remaining_time":1.848410998},
{"learn":[6.224773967],"iteration":53,"passed_time":0.1042752901,"remaining_time":1.8267486},
{"learn":[6.182249254],"iteration":54,"passed_time":0.1050043743,"remaining_time":1.804166067},
{"learn":[6.139904173],"iteration":55,"passed_time":0.1058050632,"remaining_time":1.783571065},
{"learn":[6.100525536],"iteration":56,"passed_time":0.1065570415,"remaining_time":1.762864738},
{"learn":[6.062568564],"iteration":57,"passed_time":0.1073214612,"remaining_time":1.743048559},
{"learn":[6.030559288],"iteration":58,"passed_time":0.1080337466,"remaining_time":1.723046704},
{"learn":[5.997931376],"iteration":59,"passed_time":0.1087905894,"remaining_time":1.704385901},
{"learn":[5.964103835],"iteration":60,"passed_time":0.1095743086,"remaining_time":1.686725833},
{"learn":[5.933729724],"iteration":61,"passed_time":0.1103284239,"remaining_time":1.669162284},
{"learn":[5.901932711],"iteration":62,"passed_time":0.1110875712,"remaining_time":1.65220721},
{"learn":[5.873727795],"iteration":63,"passed_time":0.1118503045,"remaining_time":1.635810703},
{"learn":[5.846485734],"iteration":64,"passed_time":0.1126190161,"remaining_time":1.619981232},
{"learn":[5.820630862],"iteration":65,"passed_time":0.1133701769,"remaining_time":1.604359776},
{"learn":[5.793646238],"iteration":66,"passed_time":0.1141260367,"remaining_time":1.589247645},
{"learn":[5.765388646],"iteration":67,"passed_time":0.1148619349,"remaining_time":1.574284167},
{"learn":[5.747073912],"iteration":68,"passed_time":0.1157108319,"remaining_time":1.561257746},
{"learn":[5.722315217],"iteration":69,"passed_time":0.1167264149,"remaining_time":1.550793798},
{"learn":[5.699970599],"iteration":70,"passed_time":0.1177417503,"remaining_time":1.540592761},
{"learn":[5.682732647],"iteration":71,"passed_time":0.118801788,"remaining_time":1.531223045},
{"learn":[5.663525791],"iteration":72,"passed_time":0.1195878798,"remaining_time":1.518602254},
{"learn":[5.642381613],"iteration":73,"passed_time":0.1204539419,"remaining_time":1.50730203},
{"learn":[5.621404779],"iteration":74,"passed_time":0.1212079417,"remaining_time":1.494897948},
{"learn":[5.602460129],"iteration":75,"passed_time":0.1219643087,"remaining_time":1.482829227},
{"learn":[5.587337574],"iteration":76,"passed_time":0.1226585019,"remaining_time":1.470309056},
{"learn":[5.572393026],"iteration":77,"passed_time":0.1233755959,"remaining_time":1.458362813},
{"learn":[5.558425806],"iteration":78,"passed_time":0.1241131699,"remaining_time":1.446939614},
{"learn":[5.541518902],"iteration":79,"passed_time":0.1248674006,"remaining_time":1.435975107},
{"learn":[5.526157283],"iteration":80,"passed_time":0.1256470067,"remaining_time":1.425550607},
{"learn":[5.511746977],"iteration":81,"passed_time":0.1264104387,"remaining_time":1.415180277},
{"learn":[5.504975022],"iteration":82,"passed_time":0.1268072026,"remaining_time":1.400990419},
{"learn":[5.493980522],"iteration":83,"passed_time":0.1275754598,"remaining_time":1.391180014},
{"learn":[5.480745463],"iteration":84,"passed_time":0.1283570194,"remaining_time":1.381725561},
{"learn":[5.464052013],"iteration":85,"passed_time":0.129130912,"remaining_time":1.37239132},
{"learn":[5.449143727],"iteration":86,"passed_time":0.1298710681,"remaining_time":1.36289983},
{"learn":[5.438255432],"iteration":87,"passed_time":0.1309340757,"remaining_time":1.356953148},
{"learn":[5.425927931],"iteration":88,"passed_time":0.1320718974,"remaining_time":1.351882006},
{"learn":[5.412331217],"iteration":89,"passed_time":0.1329284033,"remaining_time":1.344053855},
{"learn":[5.400691499],"iteration":90,"passed_time":0.1338444901,"remaining_time":1.336974083},
{"learn":[5.391618744],"iteration":91,"passed_time":0.134664299,"remaining_time":1.329078082},
{"learn":[5.380766572],"iteration":92,"passed_time":0.1355984935,"remaining_time":1.322449823},
{"learn":[5.372207183],"iteration":93,"passed_time":0.1364310341,"remaining_time":1.314962945},
{"learn":[5.362918837],"iteration":94,"passed_time":0.1372303849,"remaining_time":1.307299982},
{"learn":[5.348292324],"iteration":95,"passed_time":0.1380013156,"remaining_time":1.299512389},
{"learn":[5.339772295],"iteration":96,"passed_time":0.1387023595,"remaining_time":1.291218873},
{"learn":[5.331515983],"iteration":97,"passed_time":0.1394621696,"remaining_time":1.283621194},
{"learn":[5.323861644],"iteration":98,"passed_time":0.1401969072,"remaining_time":1.275933469},
{"learn":[5.313277281],"iteration":99,"passed_time":0.1409364601,"remaining_time":1.268428141},
{"learn":[5.30685627],"iteration":100,"passed_time":0.141720212,"remaining_time":1.261450204},
{"learn":[5.29652059],"iteration":101,"passed_time":0.1425060348,"remaining_time":1.254611954},
{"learn":[5.288350766],"iteration":102,"passed_time":0.1432836601,"remaining_time":1.247819836},
{"learn":[5.27993346],"iteration":103,"passed_time":0.1440159745,"remaining_time":1.240753011},
{"learn":[5.271789139],"iteration":104,"passed_time":0.1448212363,"remaining_time":1.234428634},
{"learn":[5.262684686],"iteration":105,"passed_time":0.1460066228,"remaining_time":1.231414347},
{"learn":[5.251619772],"iteration":106,"passed_time":0.1469188114,"remaining_time":1.226154193},
{"learn":[5.241012171],"iteration":107,"passed_time":0.1478995848,"remaining_time":1.221541016},
{"learn":[5.232684032],"iteration":108,"passed_time":0.1489056903,"remaining_time":1.21720156},
{"learn":[5.224267141],"iteration":109,"passed_time":0.1496970124,"remaining_time":1.211184918},
{"learn":[5.216324968],"iteration":110,"passed_time":0.1504454602,"remaining_time":1.204919046},
{"learn":[5.211102527],"iteration":111,"passed_time":0.1511858039,"remaining_time":1.198687445},
{"learn":[5.206364257],"iteration":112,"passed_time":0.1519438714,"remaining_time":1.192692159},
{"learn":[5.196937641],"iteration":113,"passed_time":0.1526920963,"remaining_time":1.186712257},
{"learn":[5.190746047],"iteration":114,"passed_time":0.1534049116,"remaining_time":1.180550841},
{"learn":[5.181885213],"iteration":115,"passed_time":0.1542200628,"remaining_time":1.175263237},
{"learn":[5.178293568],"iteration":116,"passed_time":0.1548388071,"remaining_time":1.168569801},
{"learn":[5.170991438],"iteration":117,"passed_time":0.1556134899,"remaining_time":1.163144899},
{"learn":[5.166257212],"iteration":118,"passed_time":0.1563969675,"remaining_time":1.157863264},
{"learn":[5.161421246],"iteration":119,"passed_time":0.1571705205,"remaining_time":1.152583817},
{"learn":[5.158223542],"iteration":120,"passed_time":0.1579810466,"remaining_time":1.147647438},
{"learn":[5.15470988],"iteration":121,"passed_time":0.1585961597,"remaining_time":1.141372363},
{"learn":[5.146388143],"iteration":122,"passed_time":0.1594383254,"remaining_time":1.136808223},
{"learn":[5.139529364],"iteration":123,"passed_time":0.1604948153,"remaining_time":1.133818211},
{"learn":[5.134276023],"iteration":124,"passed_time":0.1616736486,"remaining_time":1.131715541},
{"learn":[5.128536065],"iteration":125,"passed_time":0.1625340293,"remaining_time":1.127418585},
{"learn":[5.123300353],"iteration":126,"passed_time":0.1633455359,"remaining_time":1.122839786},
{"learn":[5.116200518],"iteration":127,"passed_time":0.1641591528,"remaining_time":1.118334228},
{"learn":[5.108728704],"iteration":128,"passed_time":0.1649351563,"remaining_time":1.113631947},
{"learn":[5.104075866],"iteration":129,"passed_time":0.1657055665,"remaining_time":1.108952637},
{"learn":[5.100317606],"iteration":130,"passed_time":0.1664738544,"remaining_time":1.104318927},
{"learn":[5.095814182],"iteration":131,"passed_time":0.1672938348,"remaining_time":1.100083702},
{"learn":[5.092146915],"iteration":132,"passed_time":0.1681067989,"remaining_time":1.095854095},
{"learn":[5.085258329],"iteration":133,"passed_time":0.1688981671,"remaining_time":1.091535916},
{"learn":[5.079219421],"iteration":134,"passed_time":0.1697101355,"remaining_time":1.087401979},
{"learn":[5.076476829],"iteration":135,"passed_time":0.1704042933,"remaining_time":1.082568452},
{"learn":[5.072133867],"iteration":136,"passed_time":0.1711236136,"remaining_time":1.077953858},
{"learn":[5.067031564],"iteration":137,"passed_time":0.1718603314,"remaining_time":1.073504389},
{"learn":[5.061358312],"iteration":138,"passed_time":0.1726954535,"remaining_time":1.069717881},
{"learn":[5.056759124],"iteration":139,"passed_time":0.1734344131,"remaining_time":1.065382823},
{"learn":[5.050254],"iteration":140,"passed_time":0.1742584605,"remaining_time":1.061617146},
{"learn":[5.048376474],"iteration":141,"passed_time":0.174867788,"remaining_time":1.056595508},
{"learn":[5.042603751],"iteration":142,"passed_time":0.1760234764,"remaining_time":1.054909925},
{"learn":[5.037477349],"iteration":143,"passed_time":0.1769775176,"remaining_time":1.052033021},
{"learn":[5.03230489],"iteration":144,"passed_time":0.1779543434,"remaining_time":1.04931699},
{"learn":[5.025976187],"iteration":145,"passed_time":0.1787418327,"remaining_time":1.045517295},
{"learn":[5.01952451],"iteration":146,"passed_time":0.1796260525,"remaining_time":1.042319883},
{"learn":[5.017569424],"iteration":147,"passed_time":0.180465883,"remaining_time":1.038898191},
{"learn":[5.008962367],"iteration":148,"passed_time":0.1813149401,"remaining_time":1.035563853},
{"learn":[5.003880266],"iteration":149,"passed_time":0.1821488756,"remaining_time":1.032176962},
{"learn":[4.996387564],"iteration":150,"passed_time":0.1829898253,"remaining_time":1.028863322},
{"learn":[4.993361683],"iteration":151,"passed_time":0.1837747919,"remaining_time":1.025269891},
{"learn":[4.99005752],"iteration":152,"passed_time":0.1845143767,"remaining_time":1.021461942},
{"learn":[4.986908764],"iteration":153,"passed_time":0.1853111628,"remaining_time":1.018008076},
{"learn":[4.985207175],"iteration":154,"passed_time":0.1860610154,"remaining_time":1.014332632},
{"learn":[4.979003494],"iteration":155,"passed_time":0.1868991507,"remaining_time":1.011172328},
{"learn":[4.973142217],"iteration":156,"passed_time":0.1877219495,"remaining_time":1.007959258},
{"learn":[4.967056696],"iteration":157,"passed_time":0.1885206809,"remaining_time":1.004648186},
{"learn":[4.961460696],"iteration":158,"passed_time":0.1893287845,"remaining_time":1.001418288},
{"learn":[4.954240363],"iteration":159,"passed_time":0.1904157533,"remaining_time":0.9996827048},
{"learn":[4.952320707],"iteration":160,"passed_time":0.1910057913,"remaining_time":0.9953655833},
{"learn":[4.948337777],"iteration":161,"passed_time":0.191909709,"remaining_time":0.9927181245},
{"learn":[4.943228639],"iteration":162,"passed_time":0.1928680876,"remaining_time":0.9903717136},
{"learn":[4.938545759],"iteration":163,"passed_time":0.1936687057,"remaining_time":0.9872380366},
{"learn":[4.935330572],"iteration":164,"passed_time":0.1944483819,"remaining_time":0.98402666},
{"learn":[4.932051543],"iteration":165,"passed_time":0.19524457,"remaining_time":0.9809275382},
{"learn":[4.928964153],"iteration":166,"passed_time":0.1959785007,"remaining_time":0.9775454557},
{"learn":[4.922860227],"iteration":167,"passed_time":0.1967173755,"remaining_time":0.9742193835},
{"learn":[4.917668772],"iteration":168,"passed_time":0.1975046259,"remaining_time":0.9711617995},
{"learn":[4.910365386],"iteration":169,"passed_time":0.1983172537,"remaining_time":0.9682548267},
{"learn":[4.906457206],"iteration":170,"passed_time":0.1991215184,"remaining_time":0.9653318057},
{"learn":[4.901996508],"iteration":171,"passed_time":0.1998629693,"remaining_time":0.9621310384},
{"learn":[4.896816173],"iteration":172,"passed_time":0.2006620905,"remaining_time":0.9592343865},
{"learn":[4.891123132],"iteration":173,"passed_time":0.2014518596,"remaining_time":0.9563174485},
{"learn":[4.887630202],"iteration":174,"passed_time":0.2022213288,"remaining_time":0.9533291214},
{"learn":[4.885259712],"iteration":175,"passed_time":0.2030667493,"remaining_time":0.9507215991},
{"learn":[4.880659728],"iteration":176,"passed_time":0.2038843952,"remaining_time":0.9480048432},
{"learn":[4.877299723],"iteration":177,"passed_time":0.2049184395,"remaining_time":0.9463087486},
{"learn":[4.874038772],"iteration":178,"passed_time":0.2060779606,"remaining_time":0.9451955624},
{"learn":[4.86943698],"iteration":179,"passed_time":0.206828799,"remaining_time":0.9422200844},
{"learn":[4.861268711],"iteration":180,"passed_time":0.2078615265,"remaining_time":0.9405446974},
{"learn":[4.858673056],"iteration":181,"passed_time":0.2086456102,"remaining_time":0.9377588412},
{"learn":[4.854036207],"iteration":182,"passed_time":0.2093633274,"remaining_time":0.934698571},
{"learn":[4.85130244],"iteration":183,"passed_time":0.2100666992,"remaining_time":0.9316001442},
{"learn":[4.847510084],"iteration":184,"passed_time":0.2107606494,"remaining_time":0.9284861043},
{"learn":[4.845691673],"iteration":185,"passed_time":0.2114568935,"remaining_time":0.9254081254},
{"learn":[4.842058646],"iteration":186,"passed_time":0.2121980401,"remaining_time":0.9225508374},
{"learn":[4.838623675],"iteration":187,"passed_time":0.2128800194,"remaining_time":0.9194605094},
{"learn":[4.834602161],"iteration":188,"passed_time":0.2137585804,"remaining_time":0.9172391996},
{"learn":[4.830858976],"iteration":189,"passed_time":0.2144878401,"remaining_time":0.9143955291},
{"learn":[4.827590511],"iteration":190,"passed_time":0.2152935331,"remaining_time":0.9118977397},
{"learn":[4.822246226],"iteration":191,"passed_time":0.2160950068,"remaining_time":0.9093998205},
{"learn":[4.816686395],"iteration":192,"passed_time":0.2168305654,"remaining_time":0.9066438666},
{"learn":[4.814797121],"iteration":193,"passed_time":0.2175620235,"remaining_time":0.9038917058},
{"learn":[4.811639392],"iteration":194,"passed_time":0.2182392857,"remaining_time":0.9009365385},
{"learn":[4.804813432],"iteration":195,"passed_time":0.2191602398,"remaining_time":0.8990042492},
{"learn":[4.80251613],"iteration":196,"passed_time":0.2201188673,"remaining_time":0.8972357892},
{"learn":[4.800087884],"iteration":197,"passed_time":0.2210266953,"remaining_time":0.8952697456},
{"learn":[4.794773135],"iteration":198,"passed_time":0.2218835108,"remaining_time":0.8931090058},
{"learn":[4.791664833],"iteration":199,"passed_time":0.2226635434,"remaining_time":0.8906541735},
{"learn":[4.785989873],"iteration":200,"passed_time":0.2233970477,"remaining_time":0.8880310503},
{"learn":[4.782387142],"iteration":201,"passed_time":0.2241463931,"remaining_time":0.8854892164},
{"learn":[4.778623704],"iteration":202,"passed_time":0.2249131854,"remaining_time":0.8830335407},
{"learn":[4.775772178],"iteration":203,"passed_time":0.2256073292,"remaining_time":0.8803109512},
{"learn":[4.77023101],"iteration":204,"passed_time":0.2263779062,"remaining_time":0.8779045632},
{"learn":[4.764496689],"iteration":205,"passed_time":0.2270699951,"remaining_time":0.8752115347},
{"learn":[4.763138716],"iteration":206,"passed_time":0.2277988658,"remaining_time":0.8726787467},
{"learn":[4.758053283],"iteration":207,"passed_time":0.2285933393,"remaining_time":0.8704130996},
{"learn":[4.755063788],"iteration":208,"passed_time":0.2293059043,"remaining_time":0.8678515326},
{"learn":[4.752465267],"iteration":209,"passed_time":0.2300039003,"remaining_time":0.8652527677},
{"learn":[4.748067377],"iteration":210,"passed_time":0.2306971031,"remaining_time":0.8626540963},
{"learn":[4.744163298],"iteration":211,"passed_time":0.2314270996,"remaining_time":0.8602101627},
{"learn":[4.736670896],"iteration":212,"passed_time":0.2321253465,"remaining_time":0.8576650126},
{"learn":[4.73349255],"iteration":213,"passed_time":0.2328339452,"remaining_time":0.8551751447},
{"learn":[4.731864595],"iteration":214,"passed_time":0.2335687116,"remaining_time":0.8527973888},
{"learn":[4.728398311],"iteration":215,"passed_time":0.2346064318,"remaining_time":0.8515344563},
{"learn":[4.723865975],"iteration":216,"passed_time":0.2358533461,"remaining_time":0.8510284331},
{"learn":[4.723483365],"iteration":217,"passed_time":0.2367343377,"remaining_time":0.8492029912},
{"learn":[4.72095416],"iteration":218,"passed_time":0.2375406814,"remaining_time":0.8471199641},
{"learn":[4.716173382],"iteration":219,"passed_time":0.2382221268,"remaining_time":0.8446057222},
{"learn":[4.710563974],"iteration":220,"passed_time":0.2389620354,"remaining_time":0.8423141427},
{"learn":[4.707160263],"iteration":221,"passed_time":0.239627691,"remaining_time":0.8397763227},
{"learn":[4.70408351],"iteration":222,"passed_time":0.2404408594,"remaining_time":0.8377692725},
{"learn":[4.702501831],"iteration":223,"passed_time":0.2412150684,"remaining_time":0.8356379154},
{"learn":[4.700269738],"iteration":224,"passed_time":0.2418703695,"remaining_time":0.8331090506},
{"learn":[4.695346302],"iteration":225,"passed_time":0.2426303978,"remaining_time":0.8309554333},
{"learn":[4.689769299],"iteration":226,"passed_time":0.2433473917,"remaining_time":0.8286675496},
{"learn":[4.687919514],"iteration":227,"passed_time":0.244079339,"remaining_time":0.8264440775},
{"learn":[4.682982074],"iteration":228,"passed_time":0.2447833888,"remaining_time":0.8241397064},
{"learn":[4.679578702],"iteration":229,"passed_time":0.2454887861,"remaining_time":0.8218537621},
{"learn":[4.675751423],"iteration":230,"passed_time":0.2461715956,"remaining_time":0.8195063076},
{"learn":[4.672710726],"iteration":231,"passed_time":0.2468975098,"remaining_time":0.8173158944},
{"learn":[4.6690533],"iteration":232,"passed_time":0.2477081033,"remaining_time":0.8154168037},
{"learn":[4.667595702],"iteration":233,"passed_time":0.2485473672,"remaining_time":0.8136208688},
{"learn":[4.664241291],"iteration":234,"passed_time":0.249514566,"remaining_time":0.8122495446},
{"learn":[4.662246999],"iteration":235,"passed_time":0.250774589,"remaining_time":0.8118296018},
{"learn":[4.658668443],"iteration":236,"passed_time":0.2516208645,"remaining_time":0.8100705469},
{"learn":[4.658017572],"iteration":237,"passed_time":0.2524461466,"remaining_time":0.8082519484},
{"learn":[4.657656705],"iteration":238,"passed_time":0.2531200212,"remaining_time":0.8059595654},
{"learn":[4.653242871],"iteration":239,"passed_time":0.2538637746,"remaining_time":0.8039019528},
{"learn":[4.6507302],"iteration":240,"passed_time":0.2545780875,"remaining_time":0.8017625245},
{"learn":[4.647671336],"iteration":241,"passed_time":0.2553151163,"remaining_time":0.7997060254},
{"learn":[4.645506007],"iteration":242,"passed_time":0.2560435491,"remaining_time":0.7976336078},
{"learn":[4.641297906],"iteration":243,"passed_time":0.2568922105,"remaining_time":0.7959447178},
{"learn":[4.63798107],"iteration":244,"passed_time":0.2576134135,"remaining_time":0.793869907},
{"learn":[4.635062318],"iteration":245,"passed_time":0.2583724267,"remaining_time":0.7919219909},
{"learn":[4.631606017],"iteration":246,"passed_time":0.2591275571,"remaining_time":0.7899718643},
{"learn":[4.630215494],"iteration":247,"passed_time":0.2598564624,"remaining_time":0.7879518538},
{"learn":[4.62729814],"iteration":248,"passed_time":0.2606125038,"remaining_time":0.7860240575},
{"learn":[4.624691756],"iteration":249,"passed_time":0.2613600252,"remaining_time":0.7840800756},
{"learn":[4.621840053],"iteration":250,"passed_time":0.2621416528,"remaining_time":0.7822474023},
{"learn":[4.619602091],"iteration":251,"passed_time":0.2630462954,"remaining_time":0.78078821},
{"learn":[4.613584029],"iteration":252,"passed_time":0.2640000349,"remaining_time":0.7794783639},
{"learn":[4.6119388],"iteration":253,"passed_time":0.265321838,"remaining_time":0.7792523274},
{"learn":[4.60870702],"iteration":254,"passed_time":0.2661419659,"remaining_time":0.777552018},
{"learn":[4.604771557],"iteration":255,"passed_time":0.2670607624,"remaining_time":0.7761453406},
{"learn":[4.604231277],"iteration":256,"passed_time":0.267779167,"remaining_time":0.7741631172},
{"learn":[4.600750354],"iteration":257,"passed_time":0.2684797318,"remaining_time":0.7721393836},
{"learn":[4.596488253],"iteration":258,"passed_time":0.2693338811,"remaining_time":0.7705652737},
{"learn":[4.59470784],"iteration":259,"passed_time":0.2701225356,"remaining_time":0.7688102937},
{"learn":[4.588818005],"iteration":260,"passed_time":0.2708362239,"remaining_time":0.7668504577},
{"learn":[4.585054174],"iteration":261,"passed_time":0.2715733922,"remaining_time":0.7649662726},
{"learn":[4.581471435],"iteration":262,"passed_time":0.2722820456,"remaining_time":0.7630109035},
{"learn":[4.577555199],"iteration":263,"passed_time":0.2730341033,"remaining_time":0.761185985},
{"learn":[4.57457145],"iteration":264,"passed_time":0.2737324677,"remaining_time":0.7592202405},
{"learn":[4.573029224],"iteration":265,"passed_time":0.2744909463,"remaining_time":0.7574299045},
{"learn":[4.571326203],"iteration":266,"passed_time":0.2752694172,"remaining_time":0.7557021828},
{"learn":[4.571019224],"iteration":267,"passed_time":0.2761336794,"remaining_time":0.7542158707},
{"learn":[4.565766631],"iteration":268,"passed_time":0.277066168,"remaining_time":0.7529195867},
{"learn":[4.563383471],"iteration":269,"passed_time":0.2778542199,"remaining_time":0.7512354835},
{"learn":[4.558165805],"iteration":270,"passed_time":0.2787841244,"remaining_time":0.7499395818},
{"learn":[4.55629209],"iteration":271,"passed_time":0.2800222778,"remaining_time":0.7494713906},
{"learn":[4.549383848],"iteration":272,"passed_time":0.2811368264,"remaining_time":0.7486683985},
{"learn":[4.546227503],"iteration":273,"passed_time":0.2819925254,"remaining_time":0.7471772752},
{"learn":[4.540620977],"iteration":274,"passed_time":0.2827347524,"remaining_time":0.7453916201},
{"learn":[4.532898237],"iteration":275,"passed_time":0.2834721937,"remaining_time":0.7436009718},
{"learn":[4.529757367],"iteration":276,"passed_time":0.2844009496,"remaining_time":0.7423172799},
{"learn":[4.52579294],"iteration":277,"passed_time":0.2852662596,"remaining_time":0.7408713648},
{"learn":[4.521572155],"iteration":278,"passed_time":0.2860316697,"remaining_time":0.7391714475},
{"learn":[4.518818099],"iteration":279,"passed_time":0.2867770268,"remaining_time":0.7374266404},
{"learn":[4.514012334],"iteration":280,"passed_time":0.287523706,"remaining_time":0.7356923297},
{"learn":[4.508331416],"iteration":281,"passed_time":0.2882616124,"remaining_time":0.733942687},
{"learn":[4.506038537],"iteration":282,"passed_time":0.2889806211,"remaining_time":0.7321523156},
{"learn":[4.505805643],"iteration":283,"passed_time":0.2896928971,"remaining_time":0.7303525153},
{"learn":[4.501550352],"iteration":284,"passed_time":0.290513894,"remaining_time":0.7288331024},
{"learn":[4.494692643],"iteration":285,"passed_time":0.2913760886,"remaining_time":0.7274214241},
{"learn":[4.489330245],"iteration":286,"passed_time":0.2921649447,"remaining_time":0.7258313784},
{"learn":[4.484826955],"iteration":287,"passed_time":0.2929278949,"remaining_time":0.7241828512},
{"learn":[4.478285428],"iteration":288,"passed_time":0.293770429,"remaining_time":0.7227362456},
{"learn":[4.475311671],"iteration":289,"passed_time":0.2949525852,"remaining_time":0.7221252949},
{"learn":[4.471581298],"iteration":290,"passed_time":0.2959489295,"remaining_time":0.721057701},
{"learn":[4.469164956],"iteration":291,"passed_time":0.2968253235,"remaining_time":0.7196997569},
{"learn":[4.462068024],"iteration":292,"passed_time":0.2976398773,"remaining_time":0.7181958814},
{"learn":[4.458540976],"iteration":293,"passed_time":0.2984490394,"remaining_time":0.7166837476},
{"learn":[4.455757458],"iteration":294,"passed_time":0.2992501487,"remaining_time":0.715157135},
{"learn":[4.453027414],"iteration":295,"passed_time":0.3004954859,"remaining_time":0.7146919664},
{"learn":[4.450659338],"iteration":296,"passed_time":0.3015445624,"remaining_time":0.7137569945},
{"learn":[4.444696901],"iteration":297,"passed_time":0.3023514887,"remaining_time":0.7122508224},
{"learn":[4.442052813],"iteration":298,"passed_time":0.3033130687,"remaining_time":0.7111119103},
{"learn":[4.440036756],"iteration":299,"passed_time":0.3042662583,"remaining_time":0.7099546028},
{"learn":[4.435017051],"iteration":300,"passed_time":0.3051162872,"remaining_time":0.7085590855},
{"learn":[4.429962125],"iteration":301,"passed_time":0.3059289437,"remaining_time":0.7070808036},
{"learn":[4.427666256],"iteration":302,"passed_time":0.3067638816,"remaining_time":0.7056581698},
{"learn":[4.425030004],"iteration":303,"passed_time":0.3077894974,"remaining_time":0.7046759546},
{"learn":[4.422588771],"iteration":304,"passed_time":0.3089757975,"remaining_time":0.7040596041},
{"learn":[4.418936667],"iteration":305,"passed_time":0.3108010618,"remaining_time":0.7048886826},
{"learn":[4.416887976],"iteration":306,"passed_time":0.3116844146,"remaining_time":0.7035742649},
{"learn":[4.413773354],"iteration":307,"passed_time":0.3128975357,"remaining_time":0.7030035542},
{"learn":[4.411129391],"iteration":308,"passed_time":0.3139363358,"remaining_time":0.7020388609},
{"learn":[4.40850819],"iteration":309,"passed_time":0.3148387345,"remaining_time":0.7007700865},
{"learn":[4.404880292],"iteration":310,"passed_time":0.3158485079,"remaining_time":0.6997415497},
{"learn":[4.404593827],"iteration":311,"passed_time":0.316710766,"remaining_time":0.6983878429},
{"learn":[4.402139942],"iteration":312,"passed_time":0.3176482453,"remaining_time":0.6972023786},
{"learn":[4.400284725],"iteration":313,"passed_time":0.3185066432,"remaining_time":0.6958457236},
{"learn":[4.395805521],"iteration":314,"passed_time":0.3194265355,"remaining_time":0.6946259581},
{"learn":[4.392838833],"iteration":315,"passed_time":0.3202766291,"remaining_time":0.6932570073},
{"learn":[4.389213061],"iteration":316,"passed_time":0.3212868203,"remaining_time":0.6922362721},
{"learn":[4.3861981],"iteration":317,"passed_time":0.3233291036,"remaining_time":0.6934290839},
{"learn":[4.385054234],"iteration":318,"passed_time":0.3254202611,"remaining_time":0.6947059493},
{"learn":[4.379364607],"iteration":319,"passed_time":0.3262858868,"remaining_time":0.6933575095},
{"learn":[4.378387619],"iteration":320,"passed_time":0.3274389544,"remaining_time":0.6926200935},
{"learn":[4.375816727],"iteration":321,"passed_time":0.328359765,"remaining_time":0.691391058},
{"learn":[4.374600202],"iteration":322,"passed_time":0.3291029978,"remaining_time":0.6897917323},
{"learn":[4.37098897],"iteration":323,"passed_time":0.3298775905,"remaining_time":0.688263121},
{"learn":[4.367418484],"iteration":324,"passed_time":0.330657826,"remaining_time":0.6867508693},
{"learn":[4.363584638],"iteration":325,"passed_time":0.3314164121,"remaining_time":0.6851983489},
{"learn":[4.360770706],"iteration":326,"passed_time":0.3321836014,"remaining_time":0.6836683907},
{"learn":[4.358675808],"iteration":327,"passed_time":0.3329483909,"remaining_time":0.6821381667},
{"learn":[4.354228195],"iteration":328,"passed_time":0.3336703147,"remaining_time":0.6805251707},
{"learn":[4.353773425],"iteration":329,"passed_time":0.3344277168,"remaining_time":0.6789896069},
{"learn":[4.351648009],"iteration":330,"passed_time":0.3352056645,"remaining_time":0.6775002705},
{"learn":[4.348209927],"iteration":331,"passed_time":0.3360098131,"remaining_time":0.6760679372},
{"learn":[4.345852733],"iteration":332,"passed_time":0.3368505099,"remaining_time":0.6747125828},
{"learn":[4.34237339],"iteration":333,"passed_time":0.3378234855,"remaining_time":0.6736240759},
{"learn":[4.340814362],"iteration":334,"passed_time":0.339416924,"remaining_time":0.6737679239},
{"learn":[4.339707068],"iteration":335,"passed_time":0.3404798535,"remaining_time":0.6728530439},
{"learn":[4.335430786],"iteration":336,"passed_time":0.3414852175,"remaining_time":0.6718240333},
{"learn":[4.33521887],"iteration":337,"passed_time":0.3424635122,"remaining_time":0.6707421453},
{"learn":[4.328507238],"iteration":338,"passed_time":0.3433414326,"remaining_time":0.6694651532},
{"learn":[4.326140732],"iteration":339,"passed_time":0.3443603185,"remaining_time":0.6684641476},
{"learn":[4.323785636],"iteration":340,"passed_time":0.345356012,"remaining_time":0.6674182167},
{"learn":[4.320632534],"iteration":341,"passed_time":0.3462589874,"remaining_time":0.6661941921},
{"learn":[4.31973724],"iteration":342,"passed_time":0.3471265185,"remaining_time":0.6649041476},
{"learn":[4.318000924],"iteration":343,"passed_time":0.3480143154,"remaining_time":0.6636552062},
{"learn":[4.312713628],"iteration":344,"passed_time":0.3489861832,"remaining_time":0.6625679711},
{"learn":[4.308220789],"iteration":345,"passed_time":0.3499984133,"remaining_time":0.6615576945},
{"learn":[4.305890947],"iteration":346,"passed_time":0.3510147291,"remaining_time":0.6605550954},
{"learn":[4.305137856],"iteration":347,"passed_time":0.3520985138,"remaining_time":0.6596788247},
{"learn":[4.304787172],"iteration":348,"passed_time":0.353503685,"remaining_time":0.6594008565},
{"learn":[4.30350134],"iteration":349,"passed_time":0.354643376,"remaining_time":0.6586234126},
{"learn":[4.30293809],"iteration":350,"passed_time":0.3555153199,"remaining_time":0.6573488393},
{"learn":[4.299548459],"iteration":351,"passed_time":0.3565941959,"remaining_time":0.6564574971},
{"learn":[4.294768408],"iteration":352,"passed_time":0.357502417,"remaining_time":0.6552523053},
{"learn":[4.294581479],"iteration":353,"passed_time":0.3583354742,"remaining_time":0.653911628},
{"learn":[4.292551604],"iteration":354,"passed_time":0.3591368798,"remaining_time":0.6525163028},
{"learn":[4.288628894],"iteration":355,"passed_time":0.3599407748,"remaining_time":0.6511288174},
{"learn":[4.287802767],"iteration":356,"passed_time":0.360706829,"remaining_time":0.6496764455},
{"learn":[4.284566905],"iteration":357,"passed_time":0.3614837569,"remaining_time":0.6482474076},
{"learn":[4.27890232],"iteration":358,"passed_time":0.3622972129,"remaining_time":0.6468872241},
{"learn":[4.276938023],"iteration":359,"passed_time":0.3630998832,"remaining_time":0.6455109035},
{"learn":[4.273425094],"iteration":360,"passed_time":0.3639709088,"remaining_time":0.6442587554},
{"learn":[4.269726505],"iteration":361,"passed_time":0.3647671035,"remaining_time":0.6428768288},
{"learn":[4.265565857],"iteration":362,"passed_time":0.365579509,"remaining_time":0.6415265764},
{"learn":[4.262117173],"iteration":363,"passed_time":0.3666800251,"remaining_time":0.6406826812},
{"learn":[4.259185148],"iteration":364,"passed_time":0.3680093317,"remaining_time":0.6402354126},
{"learn":[4.257668507],"iteration":365,"passed_time":0.3689035669,"remaining_time":0.6390296761},
{"learn":[4.253432436],"iteration":366,"passed_time":0.3697017745,"remaining_time":0.6376600088},
{"learn":[4.250216667],"iteration":367,"passed_time":0.3707277567,"remaining_time":0.6366846257},
{"learn":[4.24514828],"iteration":368,"passed_time":0.3715132732,"remaining_time":0.6352977653},
{"learn":[4.244015772],"iteration":369,"passed_time":0.3723021307,"remaining_time":0.6339198441},
{"learn":[4.240329192],"iteration":370,"passed_time":0.3730714023,"remaining_time":0.6325118923},
{"learn":[4.236718014],"iteration":371,"passed_time":0.373846302,"remaining_time":0.6311168754},
{"learn":[4.233495944],"iteration":372,"passed_time":0.3746300172,"remaining_time":0.6297400021},
{"learn":[4.230357491],"iteration":373,"passed_time":0.3753679069,"remaining_time":0.6282895982},
{"learn":[4.227381215],"iteration":374,"passed_time":0.3761513025,"remaining_time":0.6269188374},
{"learn":[4.226169067],"iteration":375,"passed_time":0.3769030972,"remaining_time":0.6254987571},
{"learn":[4.225963861],"iteration":376,"passed_time":0.3775959396,"remaining_time":0.623984802},
{"learn":[4.224346548],"iteration":377,"passed_time":0.3783995283,"remaining_time":0.6226574248},
{"learn":[4.222595381],"iteration":378,"passed_time":0.3791823132,"remaining_time":0.6212987242},
{"learn":[4.219700938],"iteration":379,"passed_time":0.3799538986,"remaining_time":0.6199247819},
{"learn":[4.216356207],"iteration":380,"passed_time":0.3807722853,"remaining_time":0.6186300383},
{"learn":[4.214326494],"iteration":381,"passed_time":0.3817756144,"remaining_time":0.6176369887},
{"learn":[4.212901398],"iteration":382,"passed_time":0.3830176554,"remaining_time":0.6170284422},
{"learn":[4.211331091],"iteration":383,"passed_time":0.3838075346,"remaining_time":0.6156912534},
{"learn":[4.208624791],"iteration":384,"passed_time":0.3848437525,"remaining_time":0.6147504099},
{"learn":[4.204659106],"iteration":385,"passed_time":0.3856470983,"remaining_time":0.6134386486},
{"learn":[4.202968852],"iteration":386,"passed_time":0.3864004073,"remaining_time":0.6120502576},
{"learn":[4.197261935],"iteration":387,"passed_time":0.3871149025,"remaining_time":0.6106039183},
{"learn":[4.196934403],"iteration":388,"passed_time":0.387774278,"remaining_time":0.6090747658},
{"learn":[4.192479929],"iteration":389,"passed_time":0.3885349844,"remaining_time":0.6077085653},
{"learn":[4.190243116],"iteration":390,"passed_time":0.3892675797,"remaining_time":0.6063016779},
{"learn":[4.185852431],"iteration":391,"passed_time":0.3900385192,"remaining_time":0.6049577032},
{"learn":[4.180967944],"iteration":392,"passed_time":0.390742585,"remaining_time":0.6035133565},
{"learn":[4.178283162],"iteration":393,"passed_time":0.3914689803,"remaining_time":0.6021071118},
{"learn":[4.176341157],"iteration":394,"passed_time":0.3921799596,"remaining_time":0.6006806977},
{"learn":[4.176041504],"iteration":395,"passed_time":0.3929566065,"remaining_time":0.5993580564},
{"learn":[4.175564513],"iteration":396,"passed_time":0.3936619124,"remaining_time":0.5979298065},
{"learn":[4.170830274],"iteration":397,"passed_time":0.3944711866,"remaining_time":0.596662448},
{"learn":[4.167804808],"iteration":398,"passed_time":0.3952448589,"remaining_time":0.59534376},
{"learn":[4.165860548],"iteration":399,"passed_time":0.3962151637,"remaining_time":0.5943227456},
{"learn":[4.160950571],"iteration":400,"passed_time":0.3975882122,"remaining_time":0.5939035888},
{"learn":[4.158544115],"iteration":401,"passed_time":0.3986073183,"remaining_time":0.592953175},
{"learn":[4.154448767],"iteration":402,"passed_time":0.3995441236,"remaining_time":0.5918805007},
{"learn":[4.15197457],"iteration":403,"passed_time":0.4003150296,"remaining_time":0.5905637566},
{"learn":[4.149562679],"iteration":404,"passed_time":0.4010056923,"remaining_time":0.5891318196},
{"learn":[4.149327961],"iteration":405,"passed_time":0.4016879673,"remaining_time":0.5876912625},
{"learn":[4.147444889],"iteration":406,"passed_time":0.4023849689,"remaining_time":0.5862758883},
{"learn":[4.147254809],"iteration":407,"passed_time":0.4030737135,"remaining_time":0.5848520549},
{"learn":[4.144589165],"iteration":408,"passed_time":0.4038216174,"remaining_time":0.5835173004},
{"learn":[4.141691034],"iteration":409,"passed_time":0.4045413508,"remaining_time":0.5821448707},
{"learn":[4.138893468],"iteration":410,"passed_time":0.4052693766,"remaining_time":0.5807875007},
{"learn":[4.136964597],"iteration":411,"passed_time":0.4059934213,"remaining_time":0.5794275042},
{"learn":[4.133773523],"iteration":412,"passed_time":0.4067132202,"remaining_time":0.5780645526},
{"learn":[4.131363444],"iteration":413,"passed_time":0.4074537981,"remaining_time":0.57673412},
{"learn":[4.130228592],"iteration":414,"passed_time":0.4082256726,"remaining_time":0.5754506469},
{"learn":[4.12884186],"iteration":415,"passed_time":0.4090292065,"remaining_time":0.5742140784},
{"learn":[4.12413494],"iteration":416,"passed_time":0.409861928,"remaining_time":0.5730203933},
{"learn":[4.119422508],"iteration":417,"passed_time":0.4107677011,"remaining_time":0.5719301484},
{"learn":[4.117038244],"iteration":418,"passed_time":0.411696198,"remaining_time":0.5708722937},
{"learn":[4.116067631],"iteration":419,"passed_time":0.4129838596,"remaining_time":0.5703110442},
{"learn":[4.110343455],"iteration":420,"passed_time":0.4139325123,"remaining_time":0.569280106},
{"learn":[4.105604544],"iteration":421,"passed_time":0.4148874979,"remaining_time":0.5682582317},
{"learn":[4.103390131],"iteration":422,"passed_time":0.4156206958,"remaining_time":0.5669341407},
{"learn":[4.096724402],"iteration":423,"passed_time":0.4163909799,"remaining_time":0.565663218},
{"learn":[4.093431279],"iteration":424,"passed_time":0.4171993911,"remaining_time":0.564446235},
{"learn":[4.091412744],"iteration":425,"passed_time":0.4179962392,"remaining_time":0.5632155899},
{"learn":[4.091192901],"iteration":426,"passed_time":0.418819387,"remaining_time":0.5620222687},
{"learn":[4.088994581],"iteration":427,"passed_time":0.4197126018,"remaining_time":0.5609243183},
{"learn":[4.087845355],"iteration":428,"passed_time":0.4205276683,"remaining_time":0.5597233067},
{"learn":[4.083650279],"iteration":429,"passed_time":0.4214137107,"remaining_time":0.5586181746},
{"learn":[4.079840652],"iteration":430,"passed_time":0.4221999239,"remaining_time":0.5573822662},
{"learn":[4.075707828],"iteration":431,"passed_time":0.423026667,"remaining_time":0.5562017288},
{"learn":[4.071345409],"iteration":432,"passed_time":0.4238780886,"remaining_time":0.5550551415},
{"learn":[4.067460475],"iteration":433,"passed_time":0.4247386102,"remaining_time":0.5539217819},
{"learn":[4.064914749],"iteration":434,"passed_time":0.4257335188,"remaining_time":0.5529642256},
{"learn":[4.063823175],"iteration":435,"passed_time":0.4267496398,"remaining_time":0.5520339377},
{"learn":[4.058898471],"iteration":436,"passed_time":0.428031118,"remaining_time":0.5514451246},
{"learn":[4.054120355],"iteration":437,"passed_time":0.4289360595,"remaining_time":0.5503700124},
{"learn":[4.052715901],"iteration":438,"passed_time":0.429889434,"remaining_time":0.5493575683},
{"learn":[4.052114167],"iteration":439,"passed_time":0.4306298558,"remaining_time":0.5480743619},
{"learn":[4.051377267],"iteration":440,"passed_time":0.4313540947,"remaining_time":0.5467731042},
{"learn":[4.049275336],"iteration":441,"passed_time":0.4321063226,"remaining_time":0.5455097919},
{"learn":[4.047099198],"iteration":442,"passed_time":0.4328754074,"remaining_time":0.5442699817},
{"learn":[4.044348685],"iteration":443,"passed_time":0.4336900533,"remaining_time":0.5430893461},
{"learn":[4.042822379],"iteration":444,"passed_time":0.434513043,"remaining_time":0.5419207615},
{"learn":[4.041258611],"iteration":445,"passed_time":0.4353344095,"remaining_time":0.5407517105},
{"learn":[4.040044254],"iteration":446,"passed_time":0.4360813931,"remaining_time":0.5394921932},
{"learn":[4.036860137],"iteration":447,"passed_time":0.4368411938,"remaining_time":0.5382507566},
{"learn":[4.036372284],"iteration":448,"passed_time":0.4376709828,"remaining_time":0.537097353},
{"learn":[4.03368231],"iteration":449,"passed_time":0.4384912195,"remaining_time":0.5359337127},
{"learn":[4.032439519],"iteration":450,"passed_time":0.4392624766,"remaining_time":0.5347119726},
{"learn":[4.032008634],"iteration":451,"passed_time":0.4400016817,"remaining_time":0.5334533663},
{"learn":[4.030034932],"iteration":452,"passed_time":0.4410078125,"remaining_time":0.5325193674},
{"learn":[4.028173412],"iteration":453,"passed_time":0.4421596687,"remaining_time":0.5317603064},
{"learn":[4.023806097],"iteration":454,"passed_time":0.443036345,"remaining_time":0.5306699078},
{"learn":[4.020239186],"iteration":455,"passed_time":0.443919194,"remaining_time":0.5295878104},
{"learn":[4.017384838],"iteration":456,"passed_time":0.4447900293,"remaining_time":0.5284923105},
{"learn":[4.016468229],"iteration":457,"passed_time":0.4455713526,"remaining_time":0.5272918627},
{"learn":[4.014530169],"iteration":458,"passed_time":0.4463615128,"remaining_time":0.5261036567},
{"learn":[4.012884822],"iteration":459,"passed_time":0.4470777945,"remaining_time":0.5248304544},
{"learn":[4.008924707],"iteration":460,"passed_time":0.4478555393,"remaining_time":0.5236315307},
{"learn":[4.008286778],"iteration":461,"passed_time":0.4486078699,"remaining_time":0.5224048355},
{"learn":[4.006444202],"iteration":462,"passed_time":0.4494552553,"remaining_time":0.5212904364},
{"learn":[4.003284363],"iteration":463,"passed_time":0.450283931,"remaining_time":0.5201555755},
{"learn":[3.999811484],"iteration":464,"passed_time":0.4510873836,"remaining_time":0.5189930112},
{"learn":[3.997483319],"iteration":465,"passed_time":0.4518890495,"remaining_time":0.5178299409},
{"learn":[3.99708333],"iteration":466,"passed_time":0.4526922184,"remaining_time":0.5166701337},
{"learn":[3.995860263],"iteration":467,"passed_time":0.4535082659,"remaining_time":0.5155264903},
{"learn":[3.994131111],"iteration":468,"passed_time":0.4542622897,"remaining_time":0.514314021},
{"learn":[3.993125499],"iteration":469,"passed_time":0.4550660639,"remaining_time":0.513159604},
{"learn":[3.992954084],"iteration":470,"passed_time":0.4560590712,"remaining_time":0.5122192116},
{"learn":[3.990635743],"iteration":471,"passed_time":0.4574033266,"remaining_time":0.5116715179},
{"learn":[3.986678254],"iteration":472,"passed_time":0.4582397207,"remaining_time":0.5105546148},
{"learn":[3.986393291],"iteration":473,"passed_time":0.4592509324,"remaining_time":0.5096328912},
{"learn":[3.986152671],"iteration":474,"passed_time":0.4599670098,"remaining_time":0.5083845898},
{"learn":[3.985596662],"iteration":475,"passed_time":0.4606862421,"remaining_time":0.5071419976},
{"learn":[3.983853457],"iteration":476,"passed_time":0.4614435241,"remaining_time":0.5059433189},
{"learn":[3.983263928],"iteration":477,"passed_time":0.4621551381,"remaining_time":0.5046966152},
{"learn":[3.980067202],"iteration":478,"passed_time":0.4629133631,"remaining_time":0.5035028438},
{"learn":[3.978115407],"iteration":479,"passed_time":0.4637135508,"remaining_time":0.5023563467},
{"learn":[3.972661644],"iteration":480,"passed_time":0.4645077386,"remaining_time":0.5012048157},
{"learn":[3.969938254],"iteration":481,"passed_time":0.4652994071,"remaining_time":0.5000520599},
{"learn":[3.968211434],"iteration":482,"passed_time":0.4660120209,"remaining_time":0.4988161797},
{"learn":[3.966113368],"iteration":483,"passed_time":0.4667950327,"remaining_time":0.4976575142},
{"learn":[3.962246044],"iteration":484,"passed_time":0.4675521058,"remaining_time":0.4964728546},
{"learn":[3.961319703],"iteration":485,"passed_time":0.468299447,"remaining_time":0.4952796621},
{"learn":[3.96078191],"iteration":486,"passed_time":0.4690232055,"remaining_time":0.4940634588},
{"learn":[3.958913633],"iteration":487,"passed_time":0.4698097484,"remaining_time":0.4929151459},
{"learn":[3.957428286],"iteration":488,"passed_time":0.4706471263,"remaining_time":0.4918214346},
{"learn":[3.952641965],"iteration":489,"passed_time":0.4719908191,"remaining_time":0.4912557504},
{"learn":[3.951486786],"iteration":490,"passed_time":0.472797758,"remaining_time":0.4901304661},
{"learn":[3.94938344],"iteration":491,"passed_time":0.4737066171,"remaining_time":0.4891117103},
{"learn":[3.947297924],"iteration":492,"passed_time":0.4745360537,"remaining_time":0.4880117226},
{"learn":[3.946284886],"iteration":493,"passed_time":0.4753185169,"remaining_time":0.4868647157},
{"learn":[3.943288204],"iteration":494,"passed_time":0.4760805247,"remaining_time":0.4856983131},
{"learn":[3.943076488],"iteration":495,"passed_time":0.4768280782,"remaining_time":0.4845188536},
{"learn":[3.942347078],"iteration":496,"passed_time":0.4774990696,"remaining_time":0.4832636459},
{"learn":[3.940251541],"iteration":497,"passed_time":0.4782617895,"remaining_time":0.4821032497},
{"learn":[3.939011019],"iteration":498,"passed_time":0.4790426036,"remaining_time":0.480962614},
{"learn":[3.938760512],"iteration":499,"passed_time":0.4797239349,"remaining_time":0.4797239349},
{"learn":[3.934522727],"iteration":500,"passed_time":0.480569928,"remaining_time":0.4786514852},
{"learn":[3.930091193],"iteration":501,"passed_time":0.481348792,"remaining_time":0.4775133435},
{"learn":[3.927671752],"iteration":502,"passed_time":0.482112565,"remaining_time":0.4763617193},
{"learn":[3.927280041],"iteration":503,"passed_time":0.4828819234,"remaining_time":0.475217131},
{"learn":[3.925987561],"iteration":504,"passed_time":0.4835937884,"remaining_time":0.4740176737},
{"learn":[3.921645957],"iteration":505,"passed_time":0.4843743508,"remaining_time":0.4728872121},
{"learn":[3.920333743],"iteration":506,"passed_time":0.4852666727,"remaining_time":0.471866804},
{"learn":[3.918659461],"iteration":507,"passed_time":0.4864714728,"remaining_time":0.4711495366},
{"learn":[3.916124385],"iteration":508,"passed_time":0.487407012,"remaining_time":0.4701706147},
{"learn":[3.913849268],"iteration":509,"passed_time":0.4882610785,"remaining_time":0.4691135853},
{"learn":[3.912826119],"iteration":510,"passed_time":0.4890971483,"remaining_time":0.4680401282},
{"learn":[3.910034145],"iteration":511,"passed_time":0.4897795641,"remaining_time":0.466821147},
{"learn":[3.90792379],"iteration":512,"passed_time":0.4908372526,"remaining_time":0.4659605108},
{"learn":[3.907823851],"iteration":513,"passed_time":0.4918976941,"remaining_time":0.4651017107},
{"learn":[3.904527401],"iteration":514,"passed_time":0.4928190266,"remaining_time":0.4641111221},
{"learn":[3.903378283],"iteration":515,"passed_time":0.4936079588,"remaining_time":0.4629966125},
{"learn":[3.902170135],"iteration":516,"passed_time":0.4945777003,"remaining_time":0.4620522809},
{"learn":[3.899435429],"iteration":517,"passed_time":0.4954358539,"remaining_time":0.4610040185},
{"learn":[3.897497505],"iteration":518,"passed_time":0.4963535585,"remaining_time":0.4600116795},
{"learn":[3.896426119],"iteration":519,"passed_time":0.4973035967,"remaining_time":0.4590494739},
{"learn":[3.896044669],"iteration":520,"passed_time":0.498138243,"remaining_time":0.4579812253},
{"learn":[3.892795942],"iteration":521,"passed_time":0.4990161219,"remaining_time":0.4569534603},
{"learn":[3.892413888],"iteration":522,"passed_time":0.5000882614,"remaining_time":0.456103443},
{"learn":[3.891738985],"iteration":523,"passed_time":0.5016531838,"remaining_time":0.4557002204},
{"learn":[3.88822057],"iteration":524,"passed_time":0.5027534996,"remaining_time":0.4548722139},
{"learn":[3.883837053],"iteration":525,"passed_time":0.5038292636,"remaining_time":0.4540210475},
{"learn":[3.881769742],"iteration":526,"passed_time":0.5046800253,"remaining_time":0.4529670815},
{"learn":[3.880356898],"iteration":527,"passed_time":0.5054883791,"remaining_time":0.4518759753},
{"learn":[3.879250273],"iteration":528,"passed_time":0.5063955891,"remaining_time":0.4508739555},
{"learn":[3.877174493],"iteration":529,"passed_time":0.507251844,"remaining_time":0.4498271069},
{"learn":[3.875854201],"iteration":530,"passed_time":0.5080731284,"remaining_time":0.448750089},
{"learn":[3.873189396],"iteration":531,"passed_time":0.508936762,"remaining_time":0.4477112869},
{"learn":[3.871583368],"iteration":532,"passed_time":0.5097208756,"remaining_time":0.4466034689},
{"learn":[3.869622679],"iteration":533,"passed_time":0.5105287456,"remaining_time":0.4455175945},
{"learn":[3.866860164],"iteration":534,"passed_time":0.5116233907,"remaining_time":0.4446820125},
{"learn":[3.864498444],"iteration":535,"passed_time":0.5127860773,"remaining_time":0.4439043654},
{"learn":[3.861416322],"iteration":536,"passed_time":0.5137830268,"remaining_time":0.4429823863},
{"learn":[3.860265769],"iteration":537,"passed_time":0.5152047566,"remaining_time":0.4424249025},
{"learn":[3.859328725],"iteration":538,"passed_time":0.516666691,"remaining_time":0.4418985985},
{"learn":[3.858521278],"iteration":539,"passed_time":0.5178560791,"remaining_time":0.44113666},
{"learn":[3.85599111],"iteration":540,"passed_time":0.5188630902,"remaining_time":0.4402184074},
{"learn":[3.852379816],"iteration":541,"passed_time":0.5197937488,"remaining_time":0.439235308},
{"learn":[3.851327537],"iteration":542,"passed_time":0.5205835279,"remaining_time":0.4381338347},
{"learn":[3.847854898],"iteration":543,"passed_time":0.5213532233,"remaining_time":0.4370166725},
{"learn":[3.847083414],"iteration":544,"passed_time":0.5220961652,"remaining_time":0.4358784498},
{"learn":[3.845397429],"iteration":545,"passed_time":0.5229719879,"remaining_time":0.4348521658},
{"learn":[3.841933528],"iteration":546,"passed_time":0.5237656138,"remaining_time":0.4337583603},
{"learn":[3.840996474],"iteration":547,"passed_time":0.5245836962,"remaining_time":0.4326858224},
{"learn":[3.838355966],"iteration":548,"passed_time":0.525338055,"remaining_time":0.431561863},
{"learn":[3.83342799],"iteration":549,"passed_time":0.5261604233,"remaining_time":0.4304948918},
{"learn":[3.828161535],"iteration":550,"passed_time":0.5268872518,"remaining_time":0.4293509547},
{"learn":[3.823502399],"iteration":551,"passed_time":0.5277724299,"remaining_time":0.4283370446},
{"learn":[3.820068862],"iteration":552,"passed_time":0.528612542,"remaining_time":0.4272871723},
{"learn":[3.817951642],"iteration":553,"passed_time":0.5295527984,"remaining_time":0.4263186788},
{"learn":[3.815785958],"iteration":554,"passed_time":0.5308436747,"remaining_time":0.4256314149},
{"learn":[3.81503012],"iteration":555,"passed_time":0.5319163007,"remaining_time":0.4247676934},
{"learn":[3.813529315],"iteration":556,"passed_time":0.5328248474,"remaining_time":0.4237727243},
{"learn":[3.808881326],"iteration":557,"passed_time":0.5337677052,"remaining_time":0.4228052432},
{"learn":[3.808740434],"iteration":558,"passed_time":0.5346375922,"remaining_time":0.4217802829},
{"learn":[3.80714352],"iteration":559,"passed_time":0.535543761,"remaining_time":0.4207843837},
{"learn":[3.80573346],"iteration":560,"passed_time":0.5364184125,"remaining_time":0.4197641409},
{"learn":[3.803370052],"iteration":561,"passed_time":0.5373133765,"remaining_time":0.4187602472},
{"learn":[3.803215211],"iteration":562,"passed_time":0.5380366605,"remaining_time":0.4176234824},
{"learn":[3.801309667],"iteration":563,"passed_time":0.5388173544,"remaining_time":0.4165325648},
{"learn":[3.800003847],"iteration":564,"passed_time":0.5396241973,"remaining_time":0.4154628776},
{"learn":[3.798026138],"iteration":565,"passed_time":0.5404328247,"remaining_time":0.4143954875},
{"learn":[3.794745847],"iteration":566,"passed_time":0.541148702,"remaining_time":0.4132581799},
{"learn":[3.794312041],"iteration":567,"passed_time":0.5419105343,"remaining_time":0.4121573078},
{"learn":[3.792205926],"iteration":568,"passed_time":0.5427775308,"remaining_time":0.4111372861},
{"learn":[3.788991061],"iteration":569,"passed_time":0.5435563254,"remaining_time":0.410051263},
{"learn":[3.787391572],"iteration":570,"passed_time":0.5445027363,"remaining_time":0.4090922485},
{"learn":[3.7826445],"iteration":571,"passed_time":0.5461937209,"remaining_time":0.4086904065},
{"learn":[3.781700331],"iteration":572,"passed_time":0.5470984809,"remaining_time":0.4076981699},
{"learn":[3.780045374],"iteration":573,"passed_time":0.5483777153,"remaining_time":0.4069841581},
{"learn":[3.775462644],"iteration":574,"passed_time":0.5491201466,"remaining_time":0.4058714127},
{"learn":[3.773711943],"iteration":575,"passed_time":0.5499178796,"remaining_time":0.4048006614},
{"learn":[3.772415806],"iteration":576,"passed_time":0.550799552,"remaining_time":0.4037923925},
{"learn":[3.770170875],"iteration":577,"passed_time":0.5515901173,"remaining_time":0.4027180441},
{"learn":[3.765166479],"iteration":578,"passed_time":0.5523732332,"remaining_time":0.4016392594},
{"learn":[3.763976102],"iteration":579,"passed_time":0.553122632,"remaining_time":0.4005370784},
{"learn":[3.760761708],"iteration":580,"passed_time":0.5539065755,"remaining_time":0.3994610243},
{"learn":[3.758155662],"iteration":581,"passed_time":0.5546569734,"remaining_time":0.3983618812},
{"learn":[3.756844548],"iteration":582,"passed_time":0.5553722587,"remaining_time":0.3972388197},
{"learn":[3.753098923],"iteration":583,"passed_time":0.5561690681,"remaining_time":0.3961752266},
{"learn":[3.751618946],"iteration":584,"passed_time":0.5569609374,"remaining_time":0.3951090411},
{"learn":[3.751398464],"iteration":585,"passed_time":0.557733612,"remaining_time":0.394030231},
{"learn":[3.749920103],"iteration":586,"passed_time":0.5586161267,"remaining_time":0.393029745},
{"learn":[3.748237465],"iteration":587,"passed_time":0.5598697548,"remaining_time":0.3922896921},
{"learn":[3.746021536],"iteration":588,"passed_time":0.5613244208,"remaining_time":0.3916881782},
{"learn":[3.74417648],"iteration":589,"passed_time":0.5622773715,"remaining_time":0.3907351225},
{"learn":[3.738788389],"iteration":590,"passed_time":0.5634825279,"remaining_time":0.3899566056},
{"learn":[3.736021611],"iteration":591,"passed_time":0.5643617483,"remaining_time":0.3889520157},
{"learn":[3.734546151],"iteration":592,"passed_time":0.5651679925,"remaining_time":0.3878977621},
{"learn":[3.733527479],"iteration":593,"passed_time":0.5658913011,"remaining_time":0.386787657},
{"learn":[3.733026392],"iteration":594,"passed_time":0.566606826,"remaining_time":0.3856735539},
{"learn":[3.730314752],"iteration":595,"passed_time":0.5674260163,"remaining_time":0.384631058},
{"learn":[3.727342596],"iteration":596,"passed_time":0.5682058406,"remaining_time":0.3835627366},
{"learn":[3.725459604],"iteration":597,"passed_time":0.5689169768,"remaining_time":0.3824492051},
{"learn":[3.723158842],"iteration":598,"passed_time":0.5697210186,"remaining_time":0.3813992128},
{"learn":[3.722362756],"iteration":599,"passed_time":0.5704833587,"remaining_time":0.3803222392},
{"learn":[3.721443615],"iteration":600,"passed_time":0.5712678228,"remaining_time":0.3792610005},
{"learn":[3.720743486],"iteration":601,"passed_time":0.5719995185,"remaining_time":0.3781657946},
{"learn":[3.720215334],"iteration":602,"passed_time":0.572707301,"remaining_time":0.3770560506},
{"learn":[3.719436563],"iteration":603,"passed_time":0.5735205888,"remaining_time":0.3760168099},
{"learn":[3.715046574],"iteration":604,"passed_time":0.57494802,"remaining_time":0.3753792858},
{"learn":[3.71443396],"iteration":605,"passed_time":0.5765753018,"remaining_time":0.3748690906},
{"learn":[3.712938941],"iteration":606,"passed_time":0.5774199442,"remaining_time":0.3738484976},
{"learn":[3.712814764],"iteration":607,"passed_time":0.5783426749,"remaining_time":0.3728788299},
{"learn":[3.71235348],"iteration":608,"passed_time":0.5792014619,"remaining_time":0.371868262},
{"learn":[3.711223749],"iteration":609,"passed_time":0.580020624,"remaining_time":0.370832858},
{"learn":[3.710755648],"iteration":610,"passed_time":0.580764328,"remaining_time":0.3697501205},
{"learn":[3.708668039],"iteration":611,"passed_time":0.5815407701,"remaining_time":0.3686892464},
{"learn":[3.705623591],"iteration":612,"passed_time":0.5822782533,"remaining_time":0.3676047048},
{"learn":[3.704045802],"iteration":613,"passed_time":0.5830307956,"remaining_time":0.3665307607},
{"learn":[3.699915209],"iteration":614,"passed_time":0.5837960468,"remaining_time":0.3654658179},
{"learn":[3.696182221],"iteration":615,"passed_time":0.5845492651,"remaining_time":0.3643943471},
{"learn":[3.694263278],"iteration":616,"passed_time":0.5852928857,"remaining_time":0.3633179501},
{"learn":[3.693810229],"iteration":617,"passed_time":0.585998604,"remaining_time":0.3622192018},
{"learn":[3.690900932],"iteration":618,"passed_time":0.5867714061,"remaining_time":0.3611630141},
{"learn":[3.688020895],"iteration":619,"passed_time":0.5875404588,"remaining_time":0.3601054425},
{"learn":[3.685491894],"iteration":620,"passed_time":0.5884994614,"remaining_time":0.3591647276},
{"learn":[3.684328128],"iteration":621,"passed_time":0.5894805751,"remaining_time":0.3582373913},
{"learn":[3.680640153],"iteration":622,"passed_time":0.591000216,"remaining_time":0.3576357647},
{"learn":[3.678932783],"iteration":623,"passed_time":0.591898523,"remaining_time":0.3566568023},
{"learn":[3.674167041],"iteration":624,"passed_time":0.5931436286,"remaining_time":0.3558861771},
{"learn":[3.672200976],"iteration":625,"passed_time":0.5940867627,"remaining_time":0.354933625},
{"learn":[3.670606604],"iteration":626,"passed_time":0.5948411222,"remaining_time":0.3538688015},
{"learn":[3.665506042],"iteration":627,"passed_time":0.5955625808,"remaining_time":0.3527854778},
{"learn":[3.664214007],"iteration":628,"passed_time":0.596328661,"remaining_time":0.3517296236},
{"learn":[3.66261643],"iteration":629,"passed_time":0.5970238486,"remaining_time":0.3506330539},
{"learn":[3.662118449],"iteration":630,"passed_time":0.5977159362,"remaining_time":0.3495359436},
{"learn":[3.660871366],"iteration":631,"passed_time":0.5984907204,"remaining_time":0.3484882676},
{"learn":[3.656695243],"iteration":632,"passed_time":0.5993110211,"remaining_time":0.3474678432},
{"learn":[3.654497801],"iteration":633,"passed_time":0.6001101717,"remaining_time":0.3464358404},
{"learn":[3.654189134],"iteration":634,"passed_time":0.6008465618,"remaining_time":0.3453684961},
{"learn":[3.653957699],"iteration":635,"passed_time":0.6015237826,"remaining_time":0.3442683284},
{"learn":[3.651920725],"iteration":636,"passed_time":0.6022539454,"remaining_time":0.343199658},
{"learn":[3.65106705],"iteration":637,"passed_time":0.6030899437,"remaining_time":0.3421920997},
{"learn":[3.650612844],"iteration":638,"passed_time":0.6042449333,"remaining_time":0.341365291},
{"learn":[3.649884732],"iteration":639,"passed_time":0.6057187987,"remaining_time":0.3407168243},
{"learn":[3.646276182],"iteration":640,"passed_time":0.606548872,"remaining_time":0.3397052185},
{"learn":[3.645808194],"iteration":641,"passed_time":0.6076851227,"remaining_time":0.3388649126},
{"learn":[3.645042989],"iteration":642,"passed_time":0.6085790816,"remaining_time":0.3378891635},
{"learn":[3.639864499],"iteration":643,"passed_time":0.6094998109,"remaining_time":0.3369284669},
{"learn":[3.637318478],"iteration":644,"passed_time":0.6102702978,"remaining_time":0.3358852027},
{"learn":[3.636344905],"iteration":645,"passed_time":0.6110327694,"remaining_time":0.3348383907},
{"learn":[3.634754643],"iteration":646,"passed_time":0.6117144591,"remaining_time":0.3337483834},
{"learn":[3.630724975],"iteration":647,"passed_time":0.612492031,"remaining_time":0.3327117205},
{"learn":[3.629408252],"iteration":648,"passed_time":0.6132746597,"remaining_time":0.331678591},
{"learn":[3.62790646],"iteration":649,"passed_time":0.6141061525,"remaining_time":0.3306725437},
{"learn":[3.627388973],"iteration":650,"passed_time":0.6148830357,"remaining_time":0.3296377565},
{"learn":[3.625163557],"iteration":651,"passed_time":0.6156719519,"remaining_time":0.3286101829},
{"learn":[3.623701985],"iteration":652,"passed_time":0.6166659683,"remaining_time":0.3276923292},
{"learn":[3.622342639],"iteration":653,"passed_time":0.6175582134,"remaining_time":0.3267204004},
{"learn":[3.621130639],"iteration":654,"passed_time":0.6186499173,"remaining_time":0.3258537732},
{"learn":[3.619125665],"iteration":655,"passed_time":0.6202628616,"remaining_time":0.3252597933},
{"learn":[3.618878783],"iteration":656,"passed_time":0.6211880282,"remaining_time":0.3243036434},
{"learn":[3.616207429],"iteration":657,"passed_time":0.6220300504,"remaining_time":0.3233043727},
{"learn":[3.61206486],"iteration":658,"passed_time":0.6228820548,"remaining_time":0.3223107446},
{"learn":[3.611955873],"iteration":659,"passed_time":0.6236210864,"remaining_time":0.3212593475},
{"learn":[3.610713743],"iteration":660,"passed_time":0.6243625807,"remaining_time":0.3202101586},
{"learn":[3.610044025],"iteration":661,"passed_time":0.6252114456,"remaining_time":0.31921672},
{"learn":[3.607342669],"iteration":662,"passed_time":0.6259773122,"remaining_time":0.3181815297},
{"learn":[3.602510618],"iteration":663,"passed_time":0.6267266476,"remaining_time":0.3171387855},
{"learn":[3.600492392],"iteration":664,"passed_time":0.6274909192,"remaining_time":0.316104448},
{"learn":[3.597171065],"iteration":665,"passed_time":0.6283324315,"remaining_time":0.3151096578},
{"learn":[3.594358798],"iteration":666,"passed_time":0.6291154987,"remaining_time":0.3140861485},
{"learn":[3.593945251],"iteration":667,"passed_time":0.6298401267,"remaining_time":0.3130343145},
{"learn":[3.593607748],"iteration":668,"passed_time":0.6306430247,"remaining_time":0.3120221841},
{"learn":[3.592238714],"iteration":669,"passed_time":0.6314590161,"remaining_time":0.3110171273},
{"learn":[3.590144654],"iteration":670,"passed_time":0.6322330729,"remaining_time":0.309992073},
{"learn":[3.587151536],"iteration":671,"passed_time":0.6331680381,"remaining_time":0.3090463043},
{"learn":[3.586070865],"iteration":672,"passed_time":0.6341226673,"remaining_time":0.3081101222},
{"learn":[3.585102746],"iteration":673,"passed_time":0.6349761666,"remaining_time":0.3071249708},
{"learn":[3.584362847],"iteration":674,"passed_time":0.6358577869,"remaining_time":0.3061537492},
{"learn":[3.581407561],"iteration":675,"passed_time":0.6366914154,"remaining_time":0.3051597908},
{"learn":[3.57919422],"iteration":676,"passed_time":0.6374759928,"remaining_time":0.3041429035},
{"learn":[3.577632204],"iteration":677,"passed_time":0.6383578187,"remaining_time":0.3031728873},
{"learn":[3.573911195],"iteration":678,"passed_time":0.6391528548,"remaining_time":0.3021621007},
{"learn":[3.573408216],"iteration":679,"passed_time":0.639925402,"remaining_time":0.3011413656},
{"learn":[3.571076482],"iteration":680,"passed_time":0.640743499,"remaining_time":0.3001426963},
{"learn":[3.568177107],"iteration":681,"passed_time":0.6415661449,"remaining_time":0.2991466776},
{"learn":[3.564824621],"iteration":682,"passed_time":0.6423782675,"remaining_time":0.2981462823},
{"learn":[3.562475026],"iteration":683,"passed_time":0.643180472,"remaining_time":0.2971418555},
{"learn":[3.561226889],"iteration":684,"passed_time":0.6440103124,"remaining_time":0.2961507276},
{"learn":[3.559383467],"iteration":685,"passed_time":0.6448893025,"remaining_time":0.2951825671},
{"learn":[3.555209766],"iteration":686,"passed_time":0.6456922319,"remaining_time":0.2941800125},
{"learn":[3.55345383],"iteration":687,"passed_time":0.6464435167,"remaining_time":0.293154618},
{"learn":[3.552300968],"iteration":688,"passed_time":0.6472338331,"remaining_time":0.2921476373},
{"learn":[3.551253986],"iteration":689,"passed_time":0.6481114617,"remaining_time":0.2911805118},
{"learn":[3.549807725],"iteration":690,"passed_time":0.6490590726,"remaining_time":0.2902449399},
{"learn":[3.547992926],"iteration":691,"passed_time":0.6498696008,"remaining_time":0.2892483194},
{"learn":[3.545438607],"iteration":692,"passed_time":0.650789943,"remaining_time":0.2883008838},
{"learn":[3.543313763],"iteration":693,"passed_time":0.6515719944,"remaining_time":0.2872925508},
{"learn":[3.542962896],"iteration":694,"passed_time":0.6523956734,"remaining_time":0.2863031373},
{"learn":[3.539800465],"iteration":695,"passed_time":0.6531455595,"remaining_time":0.2852819685},
{"learn":[3.53953187],"iteration":696,"passed_time":0.6538531077,"remaining_time":0.2842431731},
{"learn":[3.536332425],"iteration":697,"passed_time":0.6546259646,"remaining_time":0.2832335835},
{"learn":[3.534993327],"iteration":698,"passed_time":0.6553772574,"remaining_time":0.2822153855},
{"learn":[3.531637011],"iteration":699,"passed_time":0.656148028,"remaining_time":0.2812062977},
{"learn":[3.531040284],"iteration":700,"passed_time":0.6569436321,"remaining_time":0.2802084821},
{"learn":[3.529973872],"iteration":701,"passed_time":0.6577680172,"remaining_time":0.2792234603},
{"learn":[3.527325183],"iteration":702,"passed_time":0.6585996622,"remaining_time":0.2782419626},
{"learn":[3.527200815],"iteration":703,"passed_time":0.6594147727,"remaining_time":0.2772539385},
{"learn":[3.523459911],"iteration":704,"passed_time":0.6602327482,"remaining_time":0.2762676039},
{"learn":[3.522729934],"iteration":705,"passed_time":0.6609906249,"remaining_time":0.2752567191},
{"learn":[3.522260582],"iteration":706,"passed_time":0.6617269589,"remaining_time":0.2742376223},
{"learn":[3.518641591],"iteration":707,"passed_time":0.6627395647,"remaining_time":0.2733332668},
{"learn":[3.516856405],"iteration":708,"passed_time":0.6637651165,"remaining_time":0.2724339195},
{"learn":[3.515083413],"iteration":709,"passed_time":0.6645793453,"remaining_time":0.2714479016},
{"learn":[3.514671214],"iteration":710,"passed_time":0.6656405957,"remaining_time":0.2705627738},
{"learn":[3.512617621],"iteration":711,"passed_time":0.6664281063,"remaining_time":0.269566425},
{"learn":[3.510747971],"iteration":712,"passed_time":0.6671671293,"remaining_time":0.2685511446},
{"learn":[3.508149266],"iteration":713,"passed_time":0.667909959,"remaining_time":0.2675381628},
{"learn":[3.504557165],"iteration":714,"passed_time":0.6686075499,"remaining_time":0.2665079045},
{"learn":[3.501367208],"iteration":715,"passed_time":0.6693918964,"remaining_time":0.2655129869},
{"learn":[3.497593362],"iteration":716,"passed_time":0.6701828808,"remaining_time":0.2645212765},
{"learn":[3.496291169],"iteration":717,"passed_time":0.6709252587,"remaining_time":0.2635110348},
{"learn":[3.49330374],"iteration":718,"passed_time":0.6716473814,"remaining_time":0.2624936219},
{"learn":[3.490044385],"iteration":719,"passed_time":0.6723769068,"remaining_time":0.2614799082},
{"learn":[3.488891789],"iteration":720,"passed_time":0.673128817,"remaining_time":0.2604756448},
{"learn":[3.486869081],"iteration":721,"passed_time":0.673839805,"remaining_time":0.2594563238},
{"learn":[3.486303638],"iteration":722,"passed_time":0.6745743611,"remaining_time":0.2584468852},
{"learn":[3.486035862],"iteration":723,"passed_time":0.6752736798,"remaining_time":0.257424773},
{"learn":[3.482668951],"iteration":724,"passed_time":0.6760323433,"remaining_time":0.2564260613},
{"learn":[3.47820549],"iteration":725,"passed_time":0.6767865313,"remaining_time":0.2554263217},
{"learn":[3.474392283],"iteration":726,"passed_time":0.6777395794,"remaining_time":0.2545019329},
{"learn":[3.472268163],"iteration":727,"passed_time":0.6790383924,"remaining_time":0.2537066521},
{"learn":[3.471209164],"iteration":728,"passed_time":0.6799431397,"remaining_time":0.2527634991},
{"learn":[3.470049971],"iteration":729,"passed_time":0.6807317408,"remaining_time":0.2517774932},
{"learn":[3.469078654],"iteration":730,"passed_time":0.6814322488,"remaining_time":0.25075961},
{"learn":[3.468643292],"iteration":731,"passed_time":0.6821281078,"remaining_time":0.2497408919},
{"learn":[3.468134848],"iteration":732,"passed_time":0.6828571867,"remaining_time":0.2487351553},
{"learn":[3.467820182],"iteration":733,"passed_time":0.6836055137,"remaining_time":0.247737148},
{"learn":[3.465776156],"iteration":734,"passed_time":0.6843662347,"remaining_time":0.2467442887},
{"learn":[3.463037608],"iteration":735,"passed_time":0.6850633518,"remaining_time":0.2457292457},
{"learn":[3.45965637],"iteration":736,"passed_time":0.6857774318,"remaining_time":0.2447211188},
{"learn":[3.457275091],"iteration":737,"passed_time":0.6865262399,"remaining_time":0.2437261177},
{"learn":[3.455522955],"iteration":738,"passed_time":0.6872692292,"remaining_time":0.2427297278},
{"learn":[3.451270508],"iteration":739,"passed_time":0.6880317462,"remaining_time":0.2417408838},
{"learn":[3.450978947],"iteration":740,"passed_time":0.6887399371,"remaining_time":0.2407336622},
{"learn":[3.450608492],"iteration":741,"passed_time":0.689465015,"remaining_time":0.2397331184},
{"learn":[3.448122004],"iteration":742,"passed_time":0.6902624711,"remaining_time":0.2387583514},
{"learn":[3.445646714],"iteration":743,"passed_time":0.6910213922,"remaining_time":0.2377708016},
{"learn":[3.44411263],"iteration":744,"passed_time":0.6917832558,"remaining_time":0.2367848728},
{"learn":[3.443264164],"iteration":745,"passed_time":0.6929812045,"remaining_time":0.235948024},
{"learn":[3.439521363],"iteration":746,"passed_time":0.6938552119,"remaining_time":0.2350004934},
{"learn":[3.436809225],"iteration":747,"passed_time":0.6946950077,"remaining_time":0.2340416336},
{"learn":[3.435509465],"iteration":748,"passed_time":0.6956705034,"remaining_time":0.2331285666},
{"learn":[3.434450277],"iteration":749,"passed_time":0.6963979592,"remaining_time":0.2321326531},
{"learn":[3.431786753],"iteration":750,"passed_time":0.6971382408,"remaining_time":0.231141707},
{"learn":[3.430150302],"iteration":751,"passed_time":0.6979137732,"remaining_time":0.2301630529},
{"learn":[3.42696281],"iteration":752,"passed_time":0.6986991222,"remaining_time":0.2291881583},
{"learn":[3.426870334],"iteration":753,"passed_time":0.6994565997,"remaining_time":0.2282046731},
{"learn":[3.425200309],"iteration":754,"passed_time":0.7002475588,"remaining_time":0.2272326515},
{"learn":[3.423383783],"iteration":755,"passed_time":0.7010184948,"remaining_time":0.2262546465},
{"learn":[3.422752979],"iteration":756,"passed_time":0.7017280653,"remaining_time":0.2252574899},
{"learn":[3.420845924],"iteration":757,"passed_time":0.7025627883,"remaining_time":0.2243010485},
{"learn":[3.418917862],"iteration":758,"passed_time":0.7033572845,"remaining_time":0.2233321549},
{"learn":[3.417095735],"iteration":759,"passed_time":0.7041168696,"remaining_time":0.2223526957},
{"learn":[3.414391848],"iteration":760,"passed_time":0.7049231519,"remaining_time":0.22138848},
{"learn":[3.41426711],"iteration":761,"passed_time":0.7056982465,"remaining_time":0.2204149379},
{"learn":[3.411976013],"iteration":762,"passed_time":0.7064917056,"remaining_time":0.2194476202},
{"learn":[3.408614844],"iteration":763,"passed_time":0.7075026909,"remaining_time":0.2185479517},
{"learn":[3.407906721],"iteration":764,"passed_time":0.7084694546,"remaining_time":0.2176344076},
{"learn":[3.407494015],"iteration":765,"passed_time":0.7092956203,"remaining_time":0.2166777743},
{"learn":[3.406287128],"iteration":766,"passed_time":0.7101598892,"remaining_time":0.2157330563},
{"learn":[3.404600442],"iteration":767,"passed_time":0.7109192207,"remaining_time":0.2147568479},
{"learn":[3.404012662],"iteration":768,"passed_time":0.7116969001,"remaining_time":0.2137867151},
{"learn":[3.400398762],"iteration":769,"passed_time":0.7124627087,"remaining_time":0.2128135364},
{"learn":[3.399737714],"iteration":770,"passed_time":0.7131875736,"remaining_time":0.2118287346},
{"learn":[3.399185251],"iteration":771,"passed_time":0.7139513727,"remaining_time":0.2108561049},
{"learn":[3.397245411],"iteration":772,"passed_time":0.7146860282,"remaining_time":0.2098754572},
{"learn":[3.396229831],"iteration":773,"passed_time":0.7154179869,"remaining_time":0.2088946577},
{"learn":[3.394002836],"iteration":774,"passed_time":0.7161024703,"remaining_time":0.2079007172},
{"learn":[3.389617243],"iteration":775,"passed_time":0.7168375162,"remaining_time":0.2069221696},
{"learn":[3.385426488],"iteration":776,"passed_time":0.7175758831,"remaining_time":0.205945202},
{"learn":[3.385072258],"iteration":777,"passed_time":0.7182315454,"remaining_time":0.2049452482},
{"learn":[3.383842366],"iteration":778,"passed_time":0.7190255837,"remaining_time":0.2039854352},
{"learn":[3.380110746],"iteration":779,"passed_time":0.719804989,"remaining_time":0.20302192},
{"learn":[3.378595218],"iteration":780,"passed_time":0.7205170007,"remaining_time":0.2020399784},
{"learn":[3.377371219],"iteration":781,"passed_time":0.7213409921,"remaining_time":0.2010899441},
{"learn":[3.375814782],"iteration":782,"passed_time":0.722264186,"remaining_time":0.2001677246},
{"learn":[3.374195887],"iteration":783,"passed_time":0.7233823565,"remaining_time":0.1992992207},
{"learn":[3.373704309],"iteration":784,"passed_time":0.7242062605,"remaining_time":0.1983494854},
{"learn":[3.372971757],"iteration":785,"passed_time":0.7250723567,"remaining_time":0.1974115577},
{"learn":[3.371565136],"iteration":786,"passed_time":0.725813843,"remaining_time":0.1964400871},
{"learn":[3.3700309],"iteration":787,"passed_time":0.7266132845,"remaining_time":0.1954847923},
{"learn":[3.368186663],"iteration":788,"passed_time":0.7273741891,"remaining_time":0.1945195867},
{"learn":[3.366710398],"iteration":789,"passed_time":0.728175536,"remaining_time":0.1935656488},
{"learn":[3.364598042],"iteration":790,"passed_time":0.7289045481,"remaining_time":0.1925929843},
{"learn":[3.36348442],"iteration":791,"passed_time":0.7296312611,"remaining_time":0.1916203312},
{"learn":[3.362001759],"iteration":792,"passed_time":0.7303387727,"remaining_time":0.1906432862},
{"learn":[3.361580401],"iteration":793,"passed_time":0.731027205,"remaining_time":0.1896619701},
{"learn":[3.359543675],"iteration":794,"passed_time":0.7319130972,"remaining_time":0.1887323081},
{"learn":[3.35766119],"iteration":795,"passed_time":0.7327653658,"remaining_time":0.187794139},
{"learn":[3.354592969],"iteration":796,"passed_time":0.7335485385,"remaining_time":0.1868385863},
{"learn":[3.350985986],"iteration":797,"passed_time":0.7343513784,"remaining_time":0.1858884441},
{"learn":[3.349589624],"iteration":798,"passed_time":0.7351829833,"remaining_time":0.1849459069},
{"learn":[3.349110856],"iteration":799,"passed_time":0.735996428,"remaining_time":0.183999107},
{"learn":[3.345315441],"iteration":800,"passed_time":0.7369405665,"remaining_time":0.1830851095},
{"learn":[3.34397474],"iteration":801,"passed_time":0.7382213913,"remaining_time":0.182254159},
{"learn":[3.343800902],"iteration":802,"passed_time":0.7392708336,"remaining_time":0.1813653228},
{"learn":[3.342329465],"iteration":803,"passed_time":0.7406584004,"remaining_time":0.1805585155},
{"learn":[3.34220347],"iteration":804,"passed_time":0.7415441505,"remaining_time":0.1796287073},
{"learn":[3.341279219],"iteration":805,"passed_time":0.7423957891,"remaining_time":0.1786907979},
{"learn":[3.337329521],"iteration":806,"passed_time":0.7433218174,"remaining_time":0.1777708931},
{"learn":[3.336708453],"iteration":807,"passed_time":0.7442415729,"remaining_time":0.1768494827},
{"learn":[3.333252703],"iteration":808,"passed_time":0.7454447292,"remaining_time":0.1759949855},
{"learn":[3.332186769],"iteration":809,"passed_time":0.74742171,"remaining_time":0.1753211419},
{"learn":[3.330594851],"iteration":810,"passed_time":0.7484523106,"remaining_time":0.1744235348},
{"learn":[3.327867442],"iteration":811,"passed_time":0.7494095005,"remaining_time":0.1735086036},
{"learn":[3.327563111],"iteration":812,"passed_time":0.7504051473,"remaining_time":0.172602414},
{"learn":[3.326308994],"iteration":813,"passed_time":0.7514241794,"remaining_time":0.1717013481},
{"learn":[3.326249879],"iteration":814,"passed_time":0.7528550056,"remaining_time":0.1708934675},
{"learn":[3.322336238],"iteration":815,"passed_time":0.7542274795,"remaining_time":0.1700709022},
{"learn":[3.320491154],"iteration":816,"passed_time":0.7558140532,"remaining_time":0.1692949471},
{"learn":[3.320434271],"iteration":817,"passed_time":0.7568367806,"remaining_time":0.1683915576},
{"learn":[3.319609638],"iteration":818,"passed_time":0.7577304506,"remaining_time":0.1674593548},
{"learn":[3.316182682],"iteration":819,"passed_time":0.7587041938,"remaining_time":0.166544823},
{"learn":[3.313126612],"iteration":820,"passed_time":0.7596010259,"remaining_time":0.1656133784},
{"learn":[3.311222803],"iteration":821,"passed_time":0.7609375409,"remaining_time":0.164777229},
{"learn":[3.309627335],"iteration":822,"passed_time":0.7619370552,"remaining_time":0.1638673861},
{"learn":[3.307974895],"iteration":823,"passed_time":0.7627630835,"remaining_time":0.1629202703},
{"learn":[3.307321505],"iteration":824,"passed_time":0.7635412827,"remaining_time":0.1619633024},
{"learn":[3.306759087],"iteration":825,"passed_time":0.7643926497,"remaining_time":0.1610221804},
{"learn":[3.30484037],"iteration":826,"passed_time":0.7652109249,"remaining_time":0.1600743531},
{"learn":[3.30201994],"iteration":827,"passed_time":0.7661807598,"remaining_time":0.1591583221},
{"learn":[3.299302297],"iteration":828,"passed_time":0.7675845849,"remaining_time":0.1583316816},
{"learn":[3.298132671],"iteration":829,"passed_time":0.7692795631,"remaining_time":0.157563284},
{"learn":[3.296976183],"iteration":830,"passed_time":0.7701306784,"remaining_time":0.1566210405},
{"learn":[3.293144745],"iteration":831,"passed_time":0.7714123782,"remaining_time":0.155765961},
{"learn":[3.290284404],"iteration":832,"passed_time":0.7723556358,"remaining_time":0.1548420062},
{"learn":[3.288285745],"iteration":833,"passed_time":0.7732483634,"remaining_time":0.1539079476},
{"learn":[3.286662667],"iteration":834,"passed_time":0.7742035459,"remaining_time":0.1529863294},
{"learn":[3.285692682],"iteration":835,"passed_time":0.7750371296,"remaining_time":0.1520407766},
{"learn":[3.284565611],"iteration":836,"passed_time":0.7759011042,"remaining_time":0.1511014098},
{"learn":[3.283897383],"iteration":837,"passed_time":0.776688119,"remaining_time":0.1501473452},
{"learn":[3.280712855],"iteration":838,"passed_time":0.7774964375,"remaining_time":0.1491977669},
{"learn":[3.280468341],"iteration":839,"passed_time":0.7783292864,"remaining_time":0.1482531974},
{"learn":[3.277814895],"iteration":840,"passed_time":0.7794393268,"remaining_time":0.1473612996},
{"learn":[3.276316385],"iteration":841,"passed_time":0.7811127003,"remaining_time":0.1465745922},
{"learn":[3.27557063],"iteration":842,"passed_time":0.7831232888,"remaining_time":0.145848584},
{"learn":[3.27499628],"iteration":843,"passed_time":0.7840208336,"remaining_time":0.1449138034},
{"learn":[3.273569958],"iteration":844,"passed_time":0.7851091212,"remaining_time":0.1440140992},
{"learn":[3.269665595],"iteration":845,"passed_time":0.7859994469,"remaining_time":0.1430779135},
{"learn":[3.267984685],"iteration":846,"passed_time":0.7868548636,"remaining_time":0.1421355303},
{"learn":[3.267702508],"iteration":847,"passed_time":0.7879959662,"remaining_time":0.14124456},
{"learn":[3.266671924],"iteration":848,"passed_time":0.7888937299,"remaining_time":0.1403097211},
{"learn":[3.265359825],"iteration":849,"passed_time":0.7899171814,"remaining_time":0.1393971497},
{"learn":[3.2618983],"iteration":850,"passed_time":0.7908728377,"remaining_time":0.1384724475},
{"learn":[3.260456253],"iteration":851,"passed_time":0.7920402908,"remaining_time":0.1375844637},
{"learn":[3.258389147],"iteration":852,"passed_time":0.7931931627,"remaining_time":0.1366933118},
{"learn":[3.258108469],"iteration":853,"passed_time":0.7947628476,"remaining_time":0.1358728053},
{"learn":[3.256424936],"iteration":854,"passed_time":0.7961113603,"remaining_time":0.1350130377},
{"learn":[3.254817983],"iteration":855,"passed_time":0.7975279745,"remaining_time":0.1341635845},
{"learn":[3.253898449],"iteration":856,"passed_time":0.7986333244,"remaining_time":0.1332608698},
{"learn":[3.253023652],"iteration":857,"passed_time":0.7997646318,"remaining_time":0.1323619787},
{"learn":[3.252845542],"iteration":858,"passed_time":0.8008345488,"remaining_time":0.1314524696},
{"learn":[3.252316026],"iteration":859,"passed_time":0.8018270349,"remaining_time":0.1305299824},
{"learn":[3.24975301],"iteration":860,"passed_time":0.8027949057,"remaining_time":0.1296033588},
{"learn":[3.249151075],"iteration":861,"passed_time":0.8036901934,"remaining_time":0.1286650194},
{"learn":[3.246257135],"iteration":862,"passed_time":0.8046157959,"remaining_time":0.1277315922},
{"learn":[3.243826471],"iteration":863,"passed_time":0.8054758529,"remaining_time":0.1267878657},
{"learn":[3.243190653],"iteration":864,"passed_time":0.8063848355,"remaining_time":0.1258519685},
{"learn":[3.24008797],"iteration":865,"passed_time":0.8072525227,"remaining_time":0.1249097437},
{"learn":[3.240036811],"iteration":866,"passed_time":0.8081521498,"remaining_time":0.1239725905},
{"learn":[3.238676314],"iteration":867,"passed_time":0.8090230652,"remaining_time":0.1230311574},
{"learn":[3.237848782],"iteration":868,"passed_time":0.8101059169,"remaining_time":0.1221218356},
{"learn":[3.236405498],"iteration":869,"passed_time":0.8113243517,"remaining_time":0.1212323744},
{"learn":[3.233378068],"iteration":870,"passed_time":0.8123049896,"remaining_time":0.1203069388},
{"learn":[3.233169169],"iteration":871,"passed_time":0.8133865306,"remaining_time":0.119396188},
{"learn":[3.232434885],"iteration":872,"passed_time":0.8146163797,"remaining_time":0.1185066211},
{"learn":[3.229978115],"iteration":873,"passed_time":0.8158726787,"remaining_time":0.1176200887},
{"learn":[3.229648848],"iteration":874,"passed_time":0.8168583708,"remaining_time":0.116694053},
{"learn":[3.227208761],"iteration":875,"passed_time":0.8178482427,"remaining_time":0.1157684727},
{"learn":[3.226258869],"iteration":876,"passed_time":0.8188080061,"remaining_time":0.1148385231},
{"learn":[3.225331995],"iteration":877,"passed_time":0.8197999322,"remaining_time":0.1139129746},
{"learn":[3.221968268],"iteration":878,"passed_time":0.8207241238,"remaining_time":0.1129779511},
{"learn":[3.221166317],"iteration":879,"passed_time":0.8219078691,"remaining_time":0.1120783458},
{"learn":[3.220047503],"iteration":880,"passed_time":0.8231745861,"remaining_time":0.1111893028},
{"learn":[3.21982781],"iteration":881,"passed_time":0.8254341288,"remaining_time":0.1104322304},
{"learn":[3.216693405],"iteration":882,"passed_time":0.8269909885,"remaining_time":0.1095786474},
{"learn":[3.214798761],"iteration":883,"passed_time":0.8283986123,"remaining_time":0.1087038903},
{"learn":[3.214395085],"iteration":884,"passed_time":0.829384574,"remaining_time":0.1077731367},
{"learn":[3.213470696],"iteration":885,"passed_time":0.8304206865,"remaining_time":0.1068487114},
{"learn":[3.211595017],"iteration":886,"passed_time":0.8314305273,"remaining_time":0.1059206872},
{"learn":[3.210965255],"iteration":887,"passed_time":0.8324751831,"remaining_time":0.1049968699},
{"learn":[3.209413583],"iteration":888,"passed_time":0.8333994408,"remaining_time":0.1040577479},
{"learn":[3.208331683],"iteration":889,"passed_time":0.8343375908,"remaining_time":0.1031203764},
{"learn":[3.207110711],"iteration":890,"passed_time":0.8352298486,"remaining_time":0.1021773889},
{"learn":[3.204519413],"iteration":891,"passed_time":0.8361736261,"remaining_time":0.1012407529},
{"learn":[3.201421296],"iteration":892,"passed_time":0.8371244331,"remaining_time":0.1003049433},
{"learn":[3.200691259],"iteration":893,"passed_time":0.8381467621,"remaining_time":0.09937758029},
{"learn":[3.200485067],"iteration":894,"passed_time":0.8390542263,"remaining_time":0.09843652934},
{"learn":[3.197467568],"iteration":895,"passed_time":0.8403921768,"remaining_time":0.09754552053},
{"learn":[3.195838544],"iteration":896,"passed_time":0.8418856774,"remaining_time":0.09667137656},
{"learn":[3.195671746],"iteration":897,"passed_time":0.8430409653,"remaining_time":0.09575743704},
{"learn":[3.194213094],"iteration":898,"passed_time":0.8439583897,"remaining_time":0.09481623733},
{"learn":[3.192884691],"iteration":899,"passed_time":0.8451086375,"remaining_time":0.09390095972},
{"learn":[3.188364239],"iteration":900,"passed_time":0.8460004822,"remaining_time":0.09295676774},
{"learn":[3.185219478],"iteration":901,"passed_time":0.8469226856,"remaining_time":0.09201599024},
{"learn":[3.184120387],"iteration":902,"passed_time":0.847781245,"remaining_time":0.09106841724},
{"learn":[3.183725321],"iteration":903,"passed_time":0.8486929358,"remaining_time":0.09012668345},
{"learn":[3.181264554],"iteration":904,"passed_time":0.8505035489,"remaining_time":0.08927937807},
{"learn":[3.180741589],"iteration":905,"passed_time":0.8523737224,"remaining_time":0.08843612572},
{"learn":[3.179782639],"iteration":906,"passed_time":0.8581127903,"remaining_time":0.08798730926},
{"learn":[3.176377564],"iteration":907,"passed_time":0.8610088799,"remaining_time":0.08723878519},
{"learn":[3.174078182],"iteration":908,"passed_time":0.8624203092,"remaining_time":0.08633690664},
{"learn":[3.171242379],"iteration":909,"passed_time":0.8638267878,"remaining_time":0.08543341857},
{"learn":[3.170421012],"iteration":910,"passed_time":0.8652444011,"remaining_time":0.08452991404},
{"learn":[3.170087224],"iteration":911,"passed_time":0.8838628804,"remaining_time":0.08528501477},
{"learn":[3.167303059],"iteration":912,"passed_time":0.8904602707,"remaining_time":0.08485218352},
{"learn":[3.16705966],"iteration":913,"passed_time":0.8920478656,"remaining_time":0.08393448189},
{"learn":[3.165667683],"iteration":914,"passed_time":0.8935856974,"remaining_time":0.0830106932},
{"learn":[3.164689733],"iteration":915,"passed_time":0.895814842,"remaining_time":0.08214895931},
{"learn":[3.163311455],"iteration":916,"passed_time":0.8974369501,"remaining_time":0.08122929865},
{"learn":[3.159425016],"iteration":917,"passed_time":0.8989943224,"remaining_time":0.08030232509},
{"learn":[3.159327058],"iteration":918,"passed_time":0.9006033344,"remaining_time":0.07937853111},
{"learn":[3.15819426],"iteration":919,"passed_time":0.9050792645,"remaining_time":0.07870254474},
{"learn":[3.157086603],"iteration":920,"passed_time":0.9062035937,"remaining_time":0.07773081857},
{"learn":[3.153354154],"iteration":921,"passed_time":0.9072624308,"remaining_time":0.07675322082},
{"learn":[3.153261317],"iteration":922,"passed_time":0.9082345074,"remaining_time":0.07576820918},
{"learn":[3.153168454],"iteration":923,"passed_time":0.9090859104,"remaining_time":0.07477329999},
{"learn":[3.152080399],"iteration":924,"passed_time":0.9100712074,"remaining_time":0.07378955736},
{"learn":[3.151635144],"iteration":925,"passed_time":0.9110156089,"remaining_time":0.07280254326},
{"learn":[3.147762655],"iteration":926,"passed_time":0.9119359477,"remaining_time":0.07181372619},
{"learn":[3.147172317],"iteration":927,"passed_time":0.912931461,"remaining_time":0.07083088922},
{"learn":[3.146254125],"iteration":928,"passed_time":0.9141129906,"remaining_time":0.06986224148},
{"learn":[3.144869828],"iteration":929,"passed_time":0.9152444861,"remaining_time":0.06888936993},
{"learn":[3.143466218],"iteration":930,"passed_time":0.9206188955,"remaining_time":0.06823061631},
{"learn":[3.141919643],"iteration":931,"passed_time":0.9227766576,"remaining_time":0.06732705227},
{"learn":[3.141054135],"iteration":932,"passed_time":0.9241094746,"remaining_time":0.06636155927},
{"learn":[3.139390417],"iteration":933,"passed_time":0.9252615244,"remaining_time":0.065382506},
{"learn":[3.139025283],"iteration":934,"passed_time":0.9263034545,"remaining_time":0.06439542732},
{"learn":[3.137824183],"iteration":935,"passed_time":0.9271956516,"remaining_time":0.06339799327},
{"learn":[3.135620453],"iteration":936,"passed_time":0.9281507012,"remaining_time":0.06240500979},
{"learn":[3.13443178],"iteration":937,"passed_time":0.9291103511,"remaining_time":0.06141241127},
{"learn":[3.132765713],"iteration":938,"passed_time":0.9300147153,"remaining_time":0.06041629141},
{"learn":[3.131434124],"iteration":939,"passed_time":0.93087382,"remaining_time":0.05941747787},
{"learn":[3.128384262],"iteration":940,"passed_time":0.9320163261,"remaining_time":0.05843673033},
{"learn":[3.128120455],"iteration":941,"passed_time":0.9332719184,"remaining_time":0.05746260219},
{"learn":[3.126314615],"iteration":942,"passed_time":0.9341639826,"remaining_time":0.05646590351},
{"learn":[3.125409666],"iteration":943,"passed_time":0.9349686471,"remaining_time":0.05546424178},
{"learn":[3.123072589],"iteration":944,"passed_time":0.9357775449,"remaining_time":0.05446324335},
{"learn":[3.122921099],"iteration":945,"passed_time":0.9366199341,"remaining_time":0.05346456284},
{"learn":[3.122182662],"iteration":946,"passed_time":0.9375058898,"remaining_time":0.05246865064},
{"learn":[3.120040951],"iteration":947,"passed_time":0.9385034433,"remaining_time":0.05147909183},
{"learn":[3.118767799],"iteration":948,"passed_time":0.9395583955,"remaining_time":0.05049260081},
{"learn":[3.118203218],"iteration":949,"passed_time":0.9404723188,"remaining_time":0.04949854309},
{"learn":[3.116343362],"iteration":950,"passed_time":0.941337514,"remaining_time":0.0485021432},
{"learn":[3.11480829],"iteration":951,"passed_time":0.9421743866,"remaining_time":0.04750459092},
{"learn":[3.112607903],"iteration":952,"passed_time":0.943015365,"remaining_time":0.04650757834},
{"learn":[3.111661241],"iteration":953,"passed_time":0.9438684632,"remaining_time":0.04551147726},
{"learn":[3.110249676],"iteration":954,"passed_time":0.9447419093,"remaining_time":0.04451663447},
{"learn":[3.107333579],"iteration":955,"passed_time":0.9455475676,"remaining_time":0.04351892571},
{"learn":[3.107149851],"iteration":956,"passed_time":0.9463141817,"remaining_time":0.04251986396},
{"learn":[3.106867336],"iteration":957,"passed_time":0.9475708444,"remaining_time":0.04154277189},
{"learn":[3.10364681],"iteration":958,"passed_time":0.9485602772,"remaining_time":0.04055367191},
{"learn":[3.102703811],"iteration":959,"passed_time":0.9493895243,"remaining_time":0.03955789684},
{"learn":[3.101469264],"iteration":960,"passed_time":0.950206737,"remaining_time":0.03856197996},
{"learn":[3.09863569],"iteration":961,"passed_time":0.9509996301,"remaining_time":0.03756547396},
{"learn":[3.09645939],"iteration":962,"passed_time":0.951756433,"remaining_time":0.03656800417},
{"learn":[3.096240186],"iteration":963,"passed_time":0.9524611882,"remaining_time":0.03556909002},
{"learn":[3.094838828],"iteration":964,"passed_time":0.9531842973,"remaining_time":0.0345714512},
{"learn":[3.094176802],"iteration":965,"passed_time":0.9539571214,"remaining_time":0.03357613057},
{"learn":[3.093182279],"iteration":966,"passed_time":0.954760891,"remaining_time":0.03258232617},
{"learn":[3.090150687],"iteration":967,"passed_time":0.9555758179,"remaining_time":0.03158928324},
{"learn":[3.088612829],"iteration":968,"passed_time":0.9563790142,"remaining_time":0.03059623265},
{"learn":[3.087153684],"iteration":969,"passed_time":0.9572219474,"remaining_time":0.0296048025},
{"learn":[3.085866843],"iteration":970,"passed_time":0.9579391641,"remaining_time":0.02860992354},
{"learn":[3.082669094],"iteration":971,"passed_time":0.9587289639,"remaining_time":0.02761770678},
{"learn":[3.081047548],"iteration":972,"passed_time":0.9594970155,"remaining_time":0.02662530259},
{"learn":[3.079684322],"iteration":973,"passed_time":0.960307527,"remaining_time":0.02563449251},
{"learn":[3.07613431],"iteration":974,"passed_time":0.9612160577,"remaining_time":0.02464656558},
{"learn":[3.074005935],"iteration":975,"passed_time":0.9623059617,"remaining_time":0.02366326135},
{"learn":[3.072988853],"iteration":976,"passed_time":0.9633910491,"remaining_time":0.02267962552},
{"learn":[3.072344268],"iteration":977,"passed_time":0.9641942727,"remaining_time":0.02168944172},
{"learn":[3.070654438],"iteration":978,"passed_time":0.9651664275,"remaining_time":0.02070326351},
{"learn":[3.069724506],"iteration":979,"passed_time":0.965943316,"remaining_time":0.0197131289},
{"learn":[3.067763166],"iteration":980,"passed_time":0.9669920161,"remaining_time":0.01872869348},
{"learn":[3.066737893],"iteration":981,"passed_time":0.9680383751,"remaining_time":0.01774408427},
{"learn":[3.065248174],"iteration":982,"passed_time":0.9689993511,"remaining_time":0.01675787281},
{"learn":[3.063186837],"iteration":983,"passed_time":0.9698859668,"remaining_time":0.01577050352},
{"learn":[3.062880371],"iteration":984,"passed_time":0.9707442105,"remaining_time":0.01478290676},
{"learn":[3.061288645],"iteration":985,"passed_time":0.9715889737,"remaining_time":0.01379538096},
{"learn":[3.059970575],"iteration":986,"passed_time":0.9725020306,"remaining_time":0.01280904397},
{"learn":[3.059576341],"iteration":987,"passed_time":0.9734490963,"remaining_time":0.01182326838},
{"learn":[3.058175919],"iteration":988,"passed_time":0.9744108064,"remaining_time":0.01083773394},
{"learn":[3.056830702],"iteration":989,"passed_time":0.975351315,"remaining_time":0.009852033485},
{"learn":[3.056336579],"iteration":990,"passed_time":0.976903511,"remaining_time":0.008871979414},
{"learn":[3.055810414],"iteration":991,"passed_time":0.9779429204,"remaining_time":0.007886636455},
{"learn":[3.055476518],"iteration":992,"passed_time":0.9788325407,"remaining_time":0.006900128686},
{"learn":[3.053331734],"iteration":993,"passed_time":0.9798416781,"remaining_time":0.005914537292},
{"learn":[3.050890374],"iteration":994,"passed_time":0.9808791314,"remaining_time":0.004929040861},
{"learn":[3.04972623],"iteration":995,"passed_time":0.9817875667,"remaining_time":0.003942921954},
{"learn":[3.047217327],"iteration":996,"passed_time":0.9827338842,"remaining_time":0.002957072871},
{"learn":[3.047155483],"iteration":997,"passed_time":0.9835815418,"remaining_time":0.001971105294},
{"learn":[3.04430671],"iteration":998,"passed_time":0.9845135599,"remaining_time":0.0009854990589},
{"learn":[3.042664195],"iteration":999,"passed_time":0.985466277,"remaining_time":0}
]}